[
  {
    "actorImg": "https://d1u5p3l4wpay3k.cloudfront.net/dota2_gamepedia/thumb/2/27/Gary_Schwartz.png/100px-Gary_Schwartz.png.jpeg?version=b4b92bba576d1cd2be7bbbf6aec33276",
    "actor": "Gary Schwartz",
    "actorUrl": null,
    "heroAvater": "https://d1u5p3l4wpay3k.cloudfront.net/dota2_gamepedia/thumb/f/f1/Sniper_minimap_icon.png/20px-Sniper_minimap_icon.png?version=ec63f994562f3e02afe09e64a62da308",
    "heroName": "Sniper",
    "avaterMain": "https://d1u5p3l4wpay3k.cloudfront.net/dota2_gamepedia/5/51/Sniper_icon.png?version=66145fea109b121abc875d51a4a1c1c6",
    "primaryAttribute": "Agility",
    "longAvatar": "https://coding.net/u/dovahkiin/p/tempData/git/raw/master/avatar/sniper.png"
  },
  {
    "actorImg": "https://d1u5p3l4wpay3k.cloudfront.net/dota2_gamepedia/thumb/2/27/Gary_Schwartz.png/100px-Gary_Schwartz.png.jpeg?version=b4b92bba576d1cd2be7bbbf6aec33276",
    "actor": "Gary Schwartz",
    "actorUrl": null,
    "heroAvater": "https://d1u5p3l4wpay3k.cloudfront.net/dota2_gamepedia/thumb/f/f1/Sniper_minimap_icon.png/20px-Sniper_minimap_icon.png?version=ec63f994562f3e02afe09e64a62da308",
    "heroName": "Sniper",
    "avaterMain": "https://d1u5p3l4wpay3k.cloudfront.net/dota2_gamepedia/5/51/Sniper_icon.png?version=66145fea109b121abc875d51a4a1c1c6",
    "primaryAttribute": "Agility",
    "longAvatar": "https://coding.net/u/dovahkiin/p/tempData/git/raw/master/avatar/sniper.png"
  },
  {
    "headTitle": "Loadout",
    "type": "title"
  },
  {
    "voices": [
      {
        "mp3Url": [
          "https://d1u5p3l4wpay3k.cloudfront.net/dota2_gamepedia/1/11/Snip_spawn_01.mp3"
        ],
        "mp3Text": "Sniper!"
      },
      {
        "mp3Url": [
          "https://d1u5p3l4wpay3k.cloudfront.net/dota2_gamepedia/0/0a/Snip_spawn_02.mp3"
        ],
        "mp3Text": "Sniper here!"
      },
      {
        "mp3Url": [
          "https://d1u5p3l4wpay3k.cloudfront.net/dota2_gamepedia/9/99/Snip_spawn_03.mp3"
        ],
        "mp3Text": "Time for target practice."
      },
      {
        "mp3Url": [
          "https://d1u5p3l4wpay3k.cloudfront.net/dota2_gamepedia/7/75/Snip_spawn_04.mp3"
        ],
        "mp3Text": "Take your best shot. I will."
      },
      {
        "mp3Url": [
          "https://d1u5p3l4wpay3k.cloudfront.net/dota2_gamepedia/c/c9/Snip_spawn_05.mp3"
        ],
        "mp3Text": "I come: Lock, stock and barrel."
      },
      {
        "mp3Url": [
          "https://d1u5p3l4wpay3k.cloudfront.net/dota2_gamepedia/b/b1/Snip_spawn_06.mp3"
        ],
        "mp3Text": "I call the shots around here."
      },
      {
        "mp3Url": [
          "https://d1u5p3l4wpay3k.cloudfront.net/dota2_gamepedia/7/7a/Snip_move_15.mp3"
        ],
        "mp3Text": "Sure as shootin'!"
      },
      {
        "mp3Url": [
          "https://d1u5p3l4wpay3k.cloudfront.net/dota2_gamepedia/e/e2/Snip_move_24.mp3"
        ],
        "mp3Text": "Into the breach!"
      },
      {
        "mp3Url": [
          "https://d1u5p3l4wpay3k.cloudfront.net/dota2_gamepedia/d/dd/Snip_move_25.mp3"
        ],
        "mp3Text": "Run and gun!"
      },
      {
        "mp3Url": [
          "https://d1u5p3l4wpay3k.cloudfront.net/dota2_gamepedia/7/7f/Snip_attack_10.mp3"
        ],
        "mp3Text": "Gunpowder justice."
      },
      {
        "mp3Url": [
          "https://d1u5p3l4wpay3k.cloudfront.net/dota2_gamepedia/2/27/Snip_cast_01.mp3"
        ],
        "mp3Text": "My sights are set!"
      },
      {
        "mp3Url": [
          "https://d1u5p3l4wpay3k.cloudfront.net/dota2_gamepedia/a/ae/Snip_level_01.mp3"
        ],
        "mp3Text": "My aim is truer than ever!"
      }
    ]
  },
  {
    "headTitle": "Drafting",
    "type": "title"
  },
  {
    "text": "Picked",
    "type": "middle"
  },
  {
    "voices": [
      {
        "mp3Url": [
          "https://d1u5p3l4wpay3k.cloudfront.net/dota2_gamepedia/1/11/Snip_spawn_01.mp3"
        ],
        "mp3Text": "Sniper!"
      }
    ]
  },
  {
    "text": "Banned",
    "type": "middle"
  },
  {
    "voices": [
      {
        "mp3Url": [
          "https://d1u5p3l4wpay3k.cloudfront.net/dota2_gamepedia/9/9f/Snip_anger_01.mp3"
        ],
        "mp3Text": "Unh."
      }
    ]
  },
  {
    "headTitle": "Entering battle",
    "type": "title"
  },
  {
    "voices": [
      {
        "mp3Url": [
          "https://d1u5p3l4wpay3k.cloudfront.net/dota2_gamepedia/1/11/Snip_spawn_01.mp3"
        ],
        "mp3Text": "Sniper!"
      },
      {
        "mp3Url": [
          "https://d1u5p3l4wpay3k.cloudfront.net/dota2_gamepedia/0/0a/Snip_spawn_02.mp3"
        ],
        "mp3Text": "Sniper here!"
      },
      {
        "mp3Url": [
          "https://d1u5p3l4wpay3k.cloudfront.net/dota2_gamepedia/7/75/Snip_spawn_04.mp3"
        ],
        "mp3Text": "Take your best shot. I will."
      },
      {
        "mp3Url": [
          "https://d1u5p3l4wpay3k.cloudfront.net/dota2_gamepedia/c/c9/Snip_spawn_05.mp3"
        ],
        "mp3Text": "I come: Lock, stock and barrel."
      },
      {
        "mp3Url": [
          "https://d1u5p3l4wpay3k.cloudfront.net/dota2_gamepedia/b/b1/Snip_spawn_06.mp3"
        ],
        "mp3Text": "I call the shots around here."
      }
    ]
  },
  {
    "text": "Tutorial mode",
    "type": "middle"
  },
  {
    "voices": [
      {
        "mp3Url": [
          "https://d1u5p3l4wpay3k.cloudfront.net/dota2_gamepedia/8/86/Snip_spawn_07.mp3"
        ],
        "mp3Text": "Sniper here! Time for target practice."
      }
    ]
  },
  {
    "headTitle": "Taunting",
    "type": "title"
  },
  {
    "voices": [
      {
        "mp3Url": [
          "https://d1u5p3l4wpay3k.cloudfront.net/dota2_gamepedia/c/cd/Snip_inthebag_01.mp3"
        ],
        "mp3Text": "It is in the bag!"
      },
      {
        "mp3Url": [
          "https://d1u5p3l4wpay3k.cloudfront.net/dota2_gamepedia/6/61/Snip_inthebag_02.mp3"
        ],
        "mp3Text": "It is in the bag!"
      }
    ]
  },
  {
    "headTitle": "Beginning battle",
    "type": "title"
  },
  {
    "voices": [
      {
        "mp3Url": [
          "https://d1u5p3l4wpay3k.cloudfront.net/dota2_gamepedia/9/99/Snip_spawn_03.mp3"
        ],
        "mp3Text": "Time for target practice."
      }
    ]
  },
  {
    "headTitle": "Moving",
    "type": "title"
  },
  {
    "voices": [
      {
        "mp3Url": [
          "https://d1u5p3l4wpay3k.cloudfront.net/dota2_gamepedia/2/2d/Snip_move_01.mp3"
        ],
        "mp3Text": "Yeah, nyeh heh ha ha!"
      },
      {
        "mp3Url": [
          "https://d1u5p3l4wpay3k.cloudfront.net/dota2_gamepedia/7/7b/Snip_move_02.mp3"
        ],
        "mp3Text": "Yes!"
      },
      {
        "mp3Url": [
          "https://d1u5p3l4wpay3k.cloudfront.net/dota2_gamepedia/6/6e/Snip_move_03.mp3"
        ],
        "mp3Text": "Mm hm!"
      },
      {
        "mp3Url": [
          "https://d1u5p3l4wpay3k.cloudfront.net/dota2_gamepedia/6/6d/Snip_move_04.mp3"
        ],
        "mp3Text": "Ah ha."
      },
      {
        "mp3Url": [
          "https://d1u5p3l4wpay3k.cloudfront.net/dota2_gamepedia/9/90/Snip_move_05.mp3"
        ],
        "mp3Text": "Ah ha!"
      },
      {
        "mp3Url": [
          "https://d1u5p3l4wpay3k.cloudfront.net/dota2_gamepedia/d/d3/Snip_move_07.mp3"
        ],
        "mp3Text": "Ah ha!"
      },
      {
        "mp3Url": [
          "https://d1u5p3l4wpay3k.cloudfront.net/dota2_gamepedia/e/e3/Snip_move_08.mp3"
        ],
        "mp3Text": "Yes."
      },
      {
        "mp3Url": [
          "https://d1u5p3l4wpay3k.cloudfront.net/dota2_gamepedia/3/35/Snip_move_09.mp3"
        ],
        "mp3Text": "Yes."
      },
      {
        "mp3Url": [
          "https://d1u5p3l4wpay3k.cloudfront.net/dota2_gamepedia/0/03/Snip_move_10.mp3"
        ],
        "mp3Text": "Yes."
      },
      {
        "mp3Url": [
          "https://d1u5p3l4wpay3k.cloudfront.net/dota2_gamepedia/0/09/Snip_move_11.mp3"
        ],
        "mp3Text": "Ah hah."
      },
      {
        "mp3Url": [
          "https://d1u5p3l4wpay3k.cloudfront.net/dota2_gamepedia/e/e3/Snip_move_12.mp3"
        ],
        "mp3Text": "Mm hm!"
      },
      {
        "mp3Url": [
          "https://d1u5p3l4wpay3k.cloudfront.net/dota2_gamepedia/5/55/Snip_move_13.mp3"
        ],
        "mp3Text": "Yeah."
      },
      {
        "mp3Url": [
          "https://d1u5p3l4wpay3k.cloudfront.net/dota2_gamepedia/5/5a/Snip_move_14.mp3"
        ],
        "mp3Text": "Mm hm hm hm!"
      },
      {
        "mp3Url": [
          "https://d1u5p3l4wpay3k.cloudfront.net/dota2_gamepedia/7/7a/Snip_move_15.mp3"
        ],
        "mp3Text": "Sure as shootin'!"
      },
      {
        "mp3Url": [
          "https://d1u5p3l4wpay3k.cloudfront.net/dota2_gamepedia/2/29/Snip_move_16.mp3"
        ],
        "mp3Text": "A new trajectory."
      },
      {
        "mp3Url": [
          "https://d1u5p3l4wpay3k.cloudfront.net/dota2_gamepedia/e/ea/Snip_move_17.mp3"
        ],
        "mp3Text": "Spotted!"
      },
      {
        "mp3Url": [
          "https://d1u5p3l4wpay3k.cloudfront.net/dota2_gamepedia/2/2e/Snip_move_18.mp3"
        ],
        "mp3Text": "Spot on!"
      },
      {
        "mp3Url": [
          "https://d1u5p3l4wpay3k.cloudfront.net/dota2_gamepedia/b/b7/Snip_move_19.mp3"
        ],
        "mp3Text": "My spotter guides me."
      },
      {
        "mp3Url": [
          "https://d1u5p3l4wpay3k.cloudfront.net/dota2_gamepedia/c/ce/Snip_move_20.mp3"
        ],
        "mp3Text": "Line of sight."
      },
      {
        "mp3Url": [
          "https://d1u5p3l4wpay3k.cloudfront.net/dota2_gamepedia/5/53/Snip_move_21.mp3"
        ],
        "mp3Text": "As you say."
      },
      {
        "mp3Url": [
          "https://d1u5p3l4wpay3k.cloudfront.net/dota2_gamepedia/9/9b/Snip_move_22.mp3"
        ],
        "mp3Text": "Snipe hunt!"
      },
      {
        "mp3Url": [
          "https://d1u5p3l4wpay3k.cloudfront.net/dota2_gamepedia/e/e4/Snip_move_23.mp3"
        ],
        "mp3Text": "Full bore!"
      },
      {
        "mp3Url": [
          "https://d1u5p3l4wpay3k.cloudfront.net/dota2_gamepedia/e/e2/Snip_move_24.mp3"
        ],
        "mp3Text": "Into the breach!"
      },
      {
        "mp3Url": [
          "https://d1u5p3l4wpay3k.cloudfront.net/dota2_gamepedia/d/dd/Snip_move_25.mp3"
        ],
        "mp3Text": "Run and gun!"
      },
      {
        "mp3Url": [
          "https://d1u5p3l4wpay3k.cloudfront.net/dota2_gamepedia/7/77/Snip_move_26.mp3"
        ],
        "mp3Text": "Of course."
      },
      {
        "mp3Url": [
          "https://d1u5p3l4wpay3k.cloudfront.net/dota2_gamepedia/2/22/Snip_move_27.mp3"
        ],
        "mp3Text": "Of course."
      },
      {
        "mp3Url": [
          "https://d1u5p3l4wpay3k.cloudfront.net/dota2_gamepedia/3/33/Snip_move_28.mp3"
        ],
        "mp3Text": "My spotter directs."
      }
    ]
  },
  {
    "headTitle": "Attacking",
    "type": "title"
  },
  {
    "voices": [
      {
        "mp3Url": [
          "https://d1u5p3l4wpay3k.cloudfront.net/dota2_gamepedia/7/75/Snip_move_29.mp3"
        ],
        "mp3Text": "Spotted."
      },
      {
        "mp3Url": [
          "https://d1u5p3l4wpay3k.cloudfront.net/dota2_gamepedia/3/3c/Snip_attack_01.mp3"
        ],
        "mp3Text": "Attack!"
      },
      {
        "mp3Url": [
          "https://d1u5p3l4wpay3k.cloudfront.net/dota2_gamepedia/e/e9/Snip_attack_02.mp3"
        ],
        "mp3Text": "Trick shot!"
      },
      {
        "mp3Url": [
          "https://d1u5p3l4wpay3k.cloudfront.net/dota2_gamepedia/2/2e/Snip_attack_03.mp3"
        ],
        "mp3Text": "You die!"
      },
      {
        "mp3Url": [
          "https://d1u5p3l4wpay3k.cloudfront.net/dota2_gamepedia/e/e2/Snip_attack_04.mp3"
        ],
        "mp3Text": "Quick draw!"
      },
      {
        "mp3Url": [
          "https://d1u5p3l4wpay3k.cloudfront.net/dota2_gamepedia/8/8f/Snip_attack_05.mp3"
        ],
        "mp3Text": "This'll hurt."
      },
      {
        "mp3Url": [
          "https://d1u5p3l4wpay3k.cloudfront.net/dota2_gamepedia/6/60/Snip_attack_06.mp3"
        ],
        "mp3Text": "Going ballistic."
      },
      {
        "mp3Url": [
          "https://d1u5p3l4wpay3k.cloudfront.net/dota2_gamepedia/d/d7/Snip_attack_07.mp3"
        ],
        "mp3Text": "Easy shot."
      },
      {
        "mp3Url": [
          "https://d1u5p3l4wpay3k.cloudfront.net/dota2_gamepedia/7/79/Snip_attack_08.mp3"
        ],
        "mp3Text": "Shoot em up!"
      },
      {
        "mp3Url": [
          "https://d1u5p3l4wpay3k.cloudfront.net/dota2_gamepedia/9/94/Snip_attack_09.mp3"
        ],
        "mp3Text": "Take this!"
      },
      {
        "mp3Url": [
          "https://d1u5p3l4wpay3k.cloudfront.net/dota2_gamepedia/7/7f/Snip_attack_10.mp3"
        ],
        "mp3Text": "Gunpowder justice."
      },
      {
        "mp3Url": [
          "https://d1u5p3l4wpay3k.cloudfront.net/dota2_gamepedia/3/37/Snip_attack_11.mp3"
        ],
        "mp3Text": "Center of mass."
      },
      {
        "mp3Url": [
          "https://d1u5p3l4wpay3k.cloudfront.net/dota2_gamepedia/6/63/Snip_attack_12.mp3"
        ],
        "mp3Text": "Snipin'!"
      },
      {
        "mp3Url": [
          "https://d1u5p3l4wpay3k.cloudfront.net/dota2_gamepedia/7/76/Snip_tf2_05.mp3"
        ],
        "mp3Text": "Let's have a go at it!"
      },
      {
        "mp3Url": [
          "https://d1u5p3l4wpay3k.cloudfront.net/dota2_gamepedia/2/2b/Snip_lasthit_04.mp3"
        ],
        "mp3Text": "On target!"
      },
      {
        "mp3Url": [
          "https://d1u5p3l4wpay3k.cloudfront.net/dota2_gamepedia/3/3b/Snip_lasthit_06.mp3"
        ],
        "mp3Text": "Eat lead!"
      },
      {
        "mp3Url": [
          "https://d1u5p3l4wpay3k.cloudfront.net/dota2_gamepedia/2/29/Snip_lasthit_10.mp3"
        ],
        "mp3Text": "Eat lead!"
      }
    ]
  },
  {
    "headTitle": "Ordering a spell cast",
    "type": "title"
  },
  {
    "voices": [
      {
        "mp3Url": [
          "https://d1u5p3l4wpay3k.cloudfront.net/dota2_gamepedia/2/27/Snip_cast_01.mp3"
        ],
        "mp3Text": "My sights are set!"
      },
      {
        "mp3Url": [
          "https://d1u5p3l4wpay3k.cloudfront.net/dota2_gamepedia/9/9e/Snip_cast_02.mp3"
        ],
        "mp3Text": "Ready…aim…"
      },
      {
        "mp3Url": [
          "https://d1u5p3l4wpay3k.cloudfront.net/dota2_gamepedia/7/74/Snip_cast_03.mp3"
        ],
        "mp3Text": "Breathe your last!"
      }
    ]
  },
  {
    "headTitle": "Abilities",
    "type": "title"
  },
  {
    "imgUrl": "https://d1u5p3l4wpay3k.cloudfront.net/dota2_gamepedia/thumb/0/05/Shrapnel_icon.png/16px-Shrapnel_icon.png?version=2a96de8573d076ee7cb47dd0988b7f75",
    "skillName": "Shrapnel",
    "type": "skill"
  },
  {
    "text": "On cast",
    "type": "middle"
  },
  {
    "voices": [
      {
        "mp3Url": [
          "https://d1u5p3l4wpay3k.cloudfront.net/dota2_gamepedia/7/76/Snip_ability_shrapnel_01.mp3"
        ],
        "mp3Text": "Shrapnel!"
      },
      {
        "mp3Url": [
          "https://d1u5p3l4wpay3k.cloudfront.net/dota2_gamepedia/1/17/Snip_ability_shrapnel_03.mp3"
        ],
        "mp3Text": "Ho ho ha ha!"
      }
    ]
  },
  {
    "text": "On cast, 4+ heroes within area",
    "type": "middle"
  },
  {
    "voices": [
      {
        "mp3Url": [
          "https://d1u5p3l4wpay3k.cloudfront.net/dota2_gamepedia/a/aa/Snip_ability_shrapnel_02.mp3"
        ],
        "mp3Text": "Dance!"
      },
      {
        "mp3Url": [
          "https://d1u5p3l4wpay3k.cloudfront.net/dota2_gamepedia/1/14/Snip_ability_shrapnel_04.mp3"
        ],
        "mp3Text": "Look lively!"
      },
      {
        "mp3Url": [
          "https://d1u5p3l4wpay3k.cloudfront.net/dota2_gamepedia/e/e9/Snip_ability_shrapnel_05.mp3"
        ],
        "mp3Text": "Hee hee hee ha ha hee hee hee hee!"
      },
      {
        "mp3Url": [
          "https://d1u5p3l4wpay3k.cloudfront.net/dota2_gamepedia/8/8f/Snip_ability_shrapnel_06.mp3"
        ],
        "mp3Text": "Dance! Ha ha ha ha! Dance!"
      }
    ]
  },
  {
    "voices": [
      {
        "mp3Url": [
          "https://d1u5p3l4wpay3k.cloudfront.net/dota2_gamepedia/2/24/Snip_ability_shrapnel_07.mp3"
        ],
        "mp3Text": "Jump around, come on, jump around! Heh heh heh heh!"
      }
    ]
  },
  {
    "imgUrl": "https://d1u5p3l4wpay3k.cloudfront.net/dota2_gamepedia/thumb/1/16/Assassinate_icon.png/16px-Assassinate_icon.png?version=34a86873380d8d2d05a375218b84bbce",
    "skillName": "Assassinate",
    "type": "skill"
  },
  {
    "text": "During cast animation",
    "type": "middle"
  },
  {
    "voices": [
      {
        "mp3Url": [
          "https://d1u5p3l4wpay3k.cloudfront.net/dota2_gamepedia/b/b5/Snip_ability_assass_02.mp3"
        ],
        "mp3Text": "Easy as shooting gnats."
      },
      {
        "mp3Url": [
          "https://d1u5p3l4wpay3k.cloudfront.net/dota2_gamepedia/9/94/Snip_ability_assass_06.mp3"
        ],
        "mp3Text": "Spotted!"
      },
      {
        "mp3Url": [
          "https://d1u5p3l4wpay3k.cloudfront.net/dota2_gamepedia/5/54/Snip_ability_assass_07.mp3"
        ],
        "mp3Text": "Marked for death!"
      },
      {
        "mp3Url": [
          "https://d1u5p3l4wpay3k.cloudfront.net/dota2_gamepedia/0/06/Snip_ability_assass_08.mp3"
        ],
        "mp3Text": "Check it out!"
      }
    ]
  },
  {
    "text": "Killing enemy",
    "type": "middle"
  },
  {
    "voices": [
      {
        "mp3Url": [
          "https://d1u5p3l4wpay3k.cloudfront.net/dota2_gamepedia/1/1e/Snip_ability_assass_03.mp3"
        ],
        "mp3Text": "Boom headshot!"
      },
      {
        "mp3Url": [
          "https://d1u5p3l4wpay3k.cloudfront.net/dota2_gamepedia/c/c5/Snip_ability_assass_04.mp3"
        ],
        "mp3Text": "You got peeped!"
      },
      {
        "mp3Url": [
          "https://d1u5p3l4wpay3k.cloudfront.net/dota2_gamepedia/c/c4/Snip_ability_assass_05.mp3"
        ],
        "mp3Text": "You can run but you can't hide!"
      },
      {
        "mp3Url": [
          "https://d1u5p3l4wpay3k.cloudfront.net/dota2_gamepedia/4/4e/Snip_ability_assass_12.mp3"
        ],
        "mp3Text": "Did ya see that?"
      },
      {
        "mp3Url": [
          "https://d1u5p3l4wpay3k.cloudfront.net/dota2_gamepedia/f/fb/Snip_kill_03.mp3"
        ],
        "mp3Text": "Bullseye!"
      },
      {
        "mp3Url": [
          "https://d1u5p3l4wpay3k.cloudfront.net/dota2_gamepedia/e/e0/Snip_kill_08.mp3"
        ],
        "mp3Text": "Now that's what I call stoppin' power."
      },
      {
        "mp3Url": [
          "https://d1u5p3l4wpay3k.cloudfront.net/dota2_gamepedia/6/6c/Snip_kill_10.mp3"
        ],
        "mp3Text": "Kill shot!"
      },
      {
        "mp3Url": [
          "https://d1u5p3l4wpay3k.cloudfront.net/dota2_gamepedia/a/aa/Snip_kill_13.mp3"
        ],
        "mp3Text": "Parting shot—boom!"
      },
      {
        "mp3Url": [
          "https://d1u5p3l4wpay3k.cloudfront.net/dota2_gamepedia/4/41/Snip_tf2_01.mp3"
        ],
        "mp3Text": "Thanks for standing still, ganker!"
      },
      {
        "mp3Url": [
          "https://d1u5p3l4wpay3k.cloudfront.net/dota2_gamepedia/7/74/Snip_tf2_02.mp3"
        ],
        "mp3Text": "Thanks for standing still, wanker!"
      }
    ]
  },
  {
    "text": "Target survives with less than 11% health",
    "type": "middle"
  },
  {
    "voices": [
      {
        "mp3Url": [
          "https://d1u5p3l4wpay3k.cloudfront.net/dota2_gamepedia/e/e8/Snip_ability_fail_01.mp3"
        ],
        "mp3Text": "Oh!"
      },
      {
        "mp3Url": [
          "https://d1u5p3l4wpay3k.cloudfront.net/dota2_gamepedia/8/86/Snip_ability_fail_02.mp3"
        ],
        "mp3Text": "Doh!"
      },
      {
        "mp3Url": [
          "https://d1u5p3l4wpay3k.cloudfront.net/dota2_gamepedia/7/78/Snip_ability_fail_03.mp3"
        ],
        "mp3Text": "Oh what an idiot!"
      },
      {
        "mp3Url": [
          "https://d1u5p3l4wpay3k.cloudfront.net/dota2_gamepedia/b/bb/Snip_ability_fail_04.mp3"
        ],
        "mp3Text": "What the---?"
      },
      {
        "mp3Url": [
          "https://d1u5p3l4wpay3k.cloudfront.net/dota2_gamepedia/3/3b/Snip_ability_fail_05.mp3"
        ],
        "mp3Text": "What a dud!"
      },
      {
        "mp3Url": [
          "https://d1u5p3l4wpay3k.cloudfront.net/dota2_gamepedia/1/17/Snip_ability_fail_06.mp3"
        ],
        "mp3Text": "How did I miss that?"
      },
      {
        "mp3Url": [
          "https://d1u5p3l4wpay3k.cloudfront.net/dota2_gamepedia/f/ff/Snip_ability_fail_07.mp3"
        ],
        "mp3Text": "Oh, I thought I had that for sure!"
      },
      {
        "mp3Url": [
          "https://d1u5p3l4wpay3k.cloudfront.net/dota2_gamepedia/a/a7/Snip_ability_fail_08.mp3"
        ],
        "mp3Text": "I had that shot!"
      }
    ]
  },
  {
    "headTitle": "Leveling up",
    "type": "title"
  },
  {
    "voices": [
      {
        "mp3Url": [
          "https://d1u5p3l4wpay3k.cloudfront.net/dota2_gamepedia/a/ae/Snip_level_01.mp3"
        ],
        "mp3Text": "My aim is truer than ever!"
      },
      {
        "mp3Url": [
          "https://d1u5p3l4wpay3k.cloudfront.net/dota2_gamepedia/1/1f/Snip_level_02.mp3"
        ],
        "mp3Text": "Steady up!"
      },
      {
        "mp3Url": [
          "https://d1u5p3l4wpay3k.cloudfront.net/dota2_gamepedia/0/0a/Snip_level_03.mp3"
        ],
        "mp3Text": "Ooh, more powder in my shot!"
      },
      {
        "mp3Url": [
          "https://d1u5p3l4wpay3k.cloudfront.net/dota2_gamepedia/9/9e/Snip_level_04.mp3"
        ],
        "mp3Text": "Higher caliber!"
      },
      {
        "mp3Url": [
          "https://d1u5p3l4wpay3k.cloudfront.net/dota2_gamepedia/1/16/Snip_level_05.mp3"
        ],
        "mp3Text": "Ooh, skills sharpened!"
      },
      {
        "mp3Url": [
          "https://d1u5p3l4wpay3k.cloudfront.net/dota2_gamepedia/a/ac/Snip_level_06.mp3"
        ],
        "mp3Text": "Target practice, payin' off!"
      },
      {
        "mp3Url": [
          "https://d1u5p3l4wpay3k.cloudfront.net/dota2_gamepedia/e/ee/Snip_level_07.mp3"
        ],
        "mp3Text": "Ha ha ha!"
      },
      {
        "mp3Url": [
          "https://d1u5p3l4wpay3k.cloudfront.net/dota2_gamepedia/2/24/Snip_level_08.mp3"
        ],
        "mp3Text": "Ho ho!"
      },
      {
        "mp3Url": [
          "https://d1u5p3l4wpay3k.cloudfront.net/dota2_gamepedia/b/b5/Snip_level_09.mp3"
        ],
        "mp3Text": "Hee hee ha ha!"
      }
    ]
  },
  {
    "headTitle": "Killing an enemy",
    "type": "title"
  },
  {
    "voices": [
      {
        "mp3Url": [
          "https://d1u5p3l4wpay3k.cloudfront.net/dota2_gamepedia/c/ca/Snip_ability_assass_01.mp3"
        ],
        "mp3Text": "Picked em off."
      },
      {
        "mp3Url": [
          "https://d1u5p3l4wpay3k.cloudfront.net/dota2_gamepedia/4/4c/Snip_ability_assass_09.mp3"
        ],
        "mp3Text": "Hoo hoo!"
      },
      {
        "mp3Url": [
          "https://d1u5p3l4wpay3k.cloudfront.net/dota2_gamepedia/c/c3/Snip_ability_assass_13.mp3"
        ],
        "mp3Text": "Ha!"
      },
      {
        "mp3Url": [
          "https://d1u5p3l4wpay3k.cloudfront.net/dota2_gamepedia/8/8f/Snip_kill_01.mp3"
        ],
        "mp3Text": "Shot to hell!"
      },
      {
        "mp3Url": [
          "https://d1u5p3l4wpay3k.cloudfront.net/dota2_gamepedia/3/38/Snip_kill_02.mp3"
        ],
        "mp3Text": "Takes one to shoot one."
      },
      {
        "mp3Url": [
          "https://d1u5p3l4wpay3k.cloudfront.net/dota2_gamepedia/b/bf/Snip_kill_04.mp3"
        ],
        "mp3Text": "Aw, don't go off half-cocked."
      },
      {
        "mp3Url": [
          "https://d1u5p3l4wpay3k.cloudfront.net/dota2_gamepedia/f/fb/Snip_kill_05.mp3"
        ],
        "mp3Text": "What a dum-dum!"
      },
      {
        "mp3Url": [
          "https://d1u5p3l4wpay3k.cloudfront.net/dota2_gamepedia/e/ed/Snip_kill_06.mp3"
        ],
        "mp3Text": "You make a great bullet catcher."
      },
      {
        "mp3Url": [
          "https://d1u5p3l4wpay3k.cloudfront.net/dota2_gamepedia/a/a2/Snip_kill_07.mp3"
        ],
        "mp3Text": "Your life's a flash in the pan."
      },
      {
        "mp3Url": [
          "https://d1u5p3l4wpay3k.cloudfront.net/dota2_gamepedia/f/f1/Snip_kill_09.mp3"
        ],
        "mp3Text": "That was your warning shot."
      },
      {
        "mp3Url": [
          "https://d1u5p3l4wpay3k.cloudfront.net/dota2_gamepedia/2/2f/Snip_kill_11.mp3"
        ],
        "mp3Text": "Ha ha ha ha!"
      },
      {
        "mp3Url": [
          "https://d1u5p3l4wpay3k.cloudfront.net/dota2_gamepedia/d/d2/Snip_kill_12.mp3"
        ],
        "mp3Text": "Hee hee hee hee hee hee hee hee hee hee!"
      },
      {
        "mp3Url": [
          "https://d1u5p3l4wpay3k.cloudfront.net/dota2_gamepedia/7/75/Snip_kill_14.mp3"
        ],
        "mp3Text": "Gunfighting's tough without a gun, isn't it?"
      },
      {
        "mp3Url": [
          "https://d1u5p3l4wpay3k.cloudfront.net/dota2_gamepedia/e/e2/Snip_tf2_03.mp3"
        ],
        "mp3Text": "Thanks for standing still."
      },
      {
        "mp3Url": [
          "https://d1u5p3l4wpay3k.cloudfront.net/dota2_gamepedia/f/fa/Snip_tf2_04.mp3"
        ],
        "mp3Text": "Say goodbye to your head!"
      },
      {
        "mp3Url": [
          "https://d1u5p3l4wpay3k.cloudfront.net/dota2_gamepedia/0/0c/Snip_tf2_07.mp3"
        ],
        "mp3Text": "I'm polite and efficient."
      },
      {
        "mp3Url": [
          "https://d1u5p3l4wpay3k.cloudfront.net/dota2_gamepedia/3/3d/Snip_laugh_01.mp3"
        ],
        "mp3Text": "Oh ho ho haw!"
      },
      {
        "mp3Url": [
          "https://d1u5p3l4wpay3k.cloudfront.net/dota2_gamepedia/b/b3/Snip_laugh_02.mp3"
        ],
        "mp3Text": "Heh heh heh!"
      },
      {
        "mp3Url": [
          "https://d1u5p3l4wpay3k.cloudfront.net/dota2_gamepedia/3/31/Snip_laugh_03.mp3"
        ],
        "mp3Text": "Ha ha ha!"
      },
      {
        "mp3Url": [
          "https://d1u5p3l4wpay3k.cloudfront.net/dota2_gamepedia/0/03/Snip_laugh_04.mp3"
        ],
        "mp3Text": "Heh heh hee hee hee."
      },
      {
        "mp3Url": [
          "https://d1u5p3l4wpay3k.cloudfront.net/dota2_gamepedia/d/d6/Snip_laugh_05.mp3"
        ],
        "mp3Text": "Ho ho ho!"
      },
      {
        "mp3Url": [
          "https://d1u5p3l4wpay3k.cloudfront.net/dota2_gamepedia/4/46/Snip_laugh_06.mp3"
        ],
        "mp3Text": "Ha ha!"
      },
      {
        "mp3Url": [
          "https://d1u5p3l4wpay3k.cloudfront.net/dota2_gamepedia/1/1f/Snip_laugh_07.mp3"
        ],
        "mp3Text": "Ha ha ha ha ha!"
      },
      {
        "mp3Url": [
          "https://d1u5p3l4wpay3k.cloudfront.net/dota2_gamepedia/7/72/Snip_laugh_09.mp3"
        ],
        "mp3Text": "Hoo hoo hoo!"
      }
    ]
  },
  {
    "text": "Killing a specific enemy",
    "type": "subTitle"
  },
  {
    "voices": [
      {
        "mp3Url": [
          "https://d1u5p3l4wpay3k.cloudfront.net/dota2_gamepedia/1/1a/Snip_kill_arrow_02.mp3"
        ],
        "mp3Text": "Oh, feather bullets!",
        "imgs": [
          {
            "img": "https://d1u5p3l4wpay3k.cloudfront.net/dota2_gamepedia/thumb/d/df/Windranger_minimap_icon.png/16px-Windranger_minimap_icon.png?version=fd41655eb4a848d263c42e723582a0ea",
            "name": "Windranger"
          }
        ]
      },
      {
        "mp3Url": [
          "https://d1u5p3l4wpay3k.cloudfront.net/dota2_gamepedia/5/5e/Snip_kill_arrow_07.mp3"
        ],
        "mp3Text": "Guns are the future, my friend!",
        "imgs": [
          {
            "img": "https://d1u5p3l4wpay3k.cloudfront.net/dota2_gamepedia/thumb/d/df/Windranger_minimap_icon.png/16px-Windranger_minimap_icon.png?version=fd41655eb4a848d263c42e723582a0ea",
            "name": "Windranger"
          }
        ]
      },
      {
        "mp3Url": [
          "https://d1u5p3l4wpay3k.cloudfront.net/dota2_gamepedia/7/78/Snip_kill_arrow_03.mp3"
        ],
        "mp3Text": "Heh, crummiest gun I've ever seen.",
        "imgs": [
          {
            "img": "https://d1u5p3l4wpay3k.cloudfront.net/dota2_gamepedia/thumb/1/16/Clinkz_minimap_icon.png/16px-Clinkz_minimap_icon.png?version=4bee48e58ab08e042b0424b06fbe1cc4",
            "name": "Clinkz"
          }
        ]
      },
      {
        "mp3Url": [
          "https://d1u5p3l4wpay3k.cloudfront.net/dota2_gamepedia/6/63/Snip_kill_arrow_04.mp3"
        ],
        "mp3Text": "What's wrong, your string break?",
        "imgs": [
          {
            "img": "https://d1u5p3l4wpay3k.cloudfront.net/dota2_gamepedia/thumb/6/63/Drow_Ranger_minimap_icon.png/16px-Drow_Ranger_minimap_icon.png?version=be7c0b5ef88fa9f514a2a9065f1d5a18",
            "name": "Drow Ranger"
          }
        ]
      },
      {
        "mp3Url": [
          "https://d1u5p3l4wpay3k.cloudfront.net/dota2_gamepedia/d/da/Snip_kill_arrow_06.mp3"
        ],
        "mp3Text": "Get a gun, you'll live longer!",
        "imgs": [
          {
            "img": "https://d1u5p3l4wpay3k.cloudfront.net/dota2_gamepedia/thumb/4/44/Lina_minimap_icon.png/16px-Lina_minimap_icon.png?version=16ce6ff9772fbac2fb0133d8220a4092",
            "name": "Lina"
          }
        ]
      },
      {
        "mp3Url": [
          "https://d1u5p3l4wpay3k.cloudfront.net/dota2_gamepedia/b/b7/Snip_kill_blade_01.mp3"
        ],
        "mp3Text": "Someone brought a knife to a gunfight!",
        "imgs": [
          {
            "img": "https://d1u5p3l4wpay3k.cloudfront.net/dota2_gamepedia/thumb/b/b2/Juggernaut_minimap_icon.png/16px-Juggernaut_minimap_icon.png?version=53939255f6c52699cd3865179b5ecfbc",
            "name": "Juggernaut"
          }
        ]
      },
      {
        "mp3Url": [
          "https://d1u5p3l4wpay3k.cloudfront.net/dota2_gamepedia/4/44/Snip_kill_blade_02.mp3"
        ],
        "mp3Text": "You pull a knife, I pull a gun.",
        "imgs": [
          {
            "img": "https://d1u5p3l4wpay3k.cloudfront.net/dota2_gamepedia/thumb/a/a4/Riki_minimap_icon.png/16px-Riki_minimap_icon.png?version=de39da8163fdddb907587d1c2703d553",
            "name": "Riki"
          }
        ]
      },
      {
        "mp3Url": [
          "https://d1u5p3l4wpay3k.cloudfront.net/dota2_gamepedia/a/a5/Snip_kill_blade_03.mp3"
        ],
        "mp3Text": "Someone brought a knife to a gunfight!",
        "imgs": [
          {
            "img": "https://d1u5p3l4wpay3k.cloudfront.net/dota2_gamepedia/thumb/a/a4/Riki_minimap_icon.png/16px-Riki_minimap_icon.png?version=de39da8163fdddb907587d1c2703d553",
            "name": "Riki"
          }
        ]
      },
      {
        "mp3Url": [
          "https://d1u5p3l4wpay3k.cloudfront.net/dota2_gamepedia/7/77/Snip_kill_arrow_05.mp3"
        ],
        "mp3Text": "Aw, isn't that quaint?"
      },
      {
        "mp3Url": [
          "https://d1u5p3l4wpay3k.cloudfront.net/dota2_gamepedia/6/68/Snip_kill_arrow_08.mp3"
        ],
        "mp3Text": "My gun is quick!"
      }
    ]
  },
  {
    "headTitle": "Last hitting",
    "type": "title"
  },
  {
    "voices": [
      {
        "mp3Url": [
          "https://d1u5p3l4wpay3k.cloudfront.net/dota2_gamepedia/b/b5/Snip_lasthit_01.mp3"
        ],
        "mp3Text": "Ah ha!"
      },
      {
        "mp3Url": [
          "https://d1u5p3l4wpay3k.cloudfront.net/dota2_gamepedia/7/7b/Snip_lasthit_02.mp3"
        ],
        "mp3Text": "A fistful of bullets!"
      },
      {
        "mp3Url": [
          "https://d1u5p3l4wpay3k.cloudfront.net/dota2_gamepedia/f/f1/Snip_lasthit_03.mp3"
        ],
        "mp3Text": "Oh a few bullets more!"
      },
      {
        "mp3Url": [
          "https://d1u5p3l4wpay3k.cloudfront.net/dota2_gamepedia/4/4a/Snip_lasthit_05.mp3"
        ],
        "mp3Text": "Gold for lead!"
      },
      {
        "mp3Url": [
          "https://d1u5p3l4wpay3k.cloudfront.net/dota2_gamepedia/5/5a/Snip_lasthit_07.mp3"
        ],
        "mp3Text": "That's gonna sting!"
      },
      {
        "mp3Url": [
          "https://d1u5p3l4wpay3k.cloudfront.net/dota2_gamepedia/a/a9/Snip_lasthit_08.mp3"
        ],
        "mp3Text": "Kill shot!"
      },
      {
        "mp3Url": [
          "https://d1u5p3l4wpay3k.cloudfront.net/dota2_gamepedia/0/0b/Snip_lasthit_09.mp3"
        ],
        "mp3Text": "Body shot!"
      }
    ]
  },
  {
    "headTitle": "Denying",
    "type": "title"
  },
  {
    "voices": [
      {
        "mp3Url": [
          "https://d1u5p3l4wpay3k.cloudfront.net/dota2_gamepedia/6/62/Snip_ability_assass_10.mp3"
        ],
        "mp3Text": "Ha ha!"
      },
      {
        "mp3Url": [
          "https://d1u5p3l4wpay3k.cloudfront.net/dota2_gamepedia/e/e9/Snip_ability_assass_11.mp3"
        ],
        "mp3Text": "ha!"
      },
      {
        "mp3Url": [
          "https://d1u5p3l4wpay3k.cloudfront.net/dota2_gamepedia/1/1d/Snip_deny_01.mp3"
        ],
        "mp3Text": "Denied!"
      },
      {
        "mp3Url": [
          "https://d1u5p3l4wpay3k.cloudfront.net/dota2_gamepedia/3/3b/Snip_deny_02.mp3"
        ],
        "mp3Text": "Denied!"
      },
      {
        "mp3Url": [
          "https://d1u5p3l4wpay3k.cloudfront.net/dota2_gamepedia/6/60/Snip_deny_03.mp3"
        ],
        "mp3Text": "Ah ah!"
      },
      {
        "mp3Url": [
          "https://d1u5p3l4wpay3k.cloudfront.net/dota2_gamepedia/f/f7/Snip_deny_04.mp3"
        ],
        "mp3Text": "Uh uh!"
      },
      {
        "mp3Url": [
          "https://d1u5p3l4wpay3k.cloudfront.net/dota2_gamepedia/d/dc/Snip_deny_05.mp3"
        ],
        "mp3Text": "Not by a long shot!"
      },
      {
        "mp3Url": [
          "https://d1u5p3l4wpay3k.cloudfront.net/dota2_gamepedia/4/4f/Snip_deny_06.mp3"
        ],
        "mp3Text": "Not for you."
      },
      {
        "mp3Url": [
          "https://d1u5p3l4wpay3k.cloudfront.net/dota2_gamepedia/2/29/Snip_deny_07.mp3"
        ],
        "mp3Text": "No no no!"
      },
      {
        "mp3Url": [
          "https://d1u5p3l4wpay3k.cloudfront.net/dota2_gamepedia/1/17/Snip_deny_08.mp3"
        ],
        "mp3Text": "Heh heh heh heh ha ha ha!"
      },
      {
        "mp3Url": [
          "https://d1u5p3l4wpay3k.cloudfront.net/dota2_gamepedia/2/2c/Snip_deny_09.mp3"
        ],
        "mp3Text": "Hee hee hee hee hee hee hee!"
      },
      {
        "mp3Url": [
          "https://d1u5p3l4wpay3k.cloudfront.net/dota2_gamepedia/2/2a/Snip_deny_10.mp3"
        ],
        "mp3Text": "Ah ha ha ha ha ha ha ha ha ha ha!"
      }
    ]
  },
  {
    "headTitle": "Acquiring an item",
    "type": "title"
  },
  {
    "voices": [
      {
        "mp3Url": [
          "https://d1u5p3l4wpay3k.cloudfront.net/dota2_gamepedia/3/3a/Snip_purch_01.mp3"
        ],
        "mp3Text": "Didn't come cheap."
      },
      {
        "mp3Url": [
          "https://d1u5p3l4wpay3k.cloudfront.net/dota2_gamepedia/e/ee/Snip_purch_02.mp3"
        ],
        "mp3Text": "Worth its weight in bullets"
      },
      {
        "mp3Url": [
          "https://d1u5p3l4wpay3k.cloudfront.net/dota2_gamepedia/7/7e/Snip_purch_03.mp3"
        ],
        "mp3Text": "Ah, this will come in handy."
      }
    ]
  },
  {
    "text": "Acquiring a specific item",
    "type": "subTitle"
  },
  {
    "voices": [
      {
        "mp3Url": [
          "https://d1u5p3l4wpay3k.cloudfront.net/dota2_gamepedia/6/63/Snip_blink_01.mp3"
        ],
        "mp3Text": "Blink dagger!",
        "imgs": [
          {
            "img": "https://d1u5p3l4wpay3k.cloudfront.net/dota2_gamepedia/thumb/4/4c/Blink_Dagger_icon.png/20px-Blink_Dagger_icon.png?version=ce8726852c7be9e04de60894546c3eb8",
            "name": "Blink Dagger (2250)"
          }
        ]
      },
      {
        "mp3Url": [
          "https://d1u5p3l4wpay3k.cloudfront.net/dota2_gamepedia/9/9b/Snip_blink_02.mp3"
        ],
        "mp3Text": "Blink and you'll miss it!",
        "imgs": [
          {
            "img": "https://d1u5p3l4wpay3k.cloudfront.net/dota2_gamepedia/thumb/4/4c/Blink_Dagger_icon.png/20px-Blink_Dagger_icon.png?version=ce8726852c7be9e04de60894546c3eb8",
            "name": "Blink Dagger (2250)"
          }
        ]
      },
      {
        "mp3Url": [
          "https://d1u5p3l4wpay3k.cloudfront.net/dota2_gamepedia/4/41/Snip_scepter_01.mp3"
        ],
        "mp3Text": "Ah, scepter!",
        "imgs": [
          {
            "img": "https://d1u5p3l4wpay3k.cloudfront.net/dota2_gamepedia/thumb/0/07/Aghanim%27s_Scepter_icon.png/20px-Aghanim%27s_Scepter_icon.png?version=1056df403356d64befeae3a47cbb12ed",
            "name": "Aghanim's Scepter (4200)"
          }
        ]
      },
      {
        "mp3Url": [
          "https://d1u5p3l4wpay3k.cloudfront.net/dota2_gamepedia/0/0c/Snip_scepter_02.mp3"
        ],
        "mp3Text": "Scepter for a sniper.",
        "imgs": [
          {
            "img": "https://d1u5p3l4wpay3k.cloudfront.net/dota2_gamepedia/thumb/0/07/Aghanim%27s_Scepter_icon.png/20px-Aghanim%27s_Scepter_icon.png?version=1056df403356d64befeae3a47cbb12ed",
            "name": "Aghanim's Scepter (4200)"
          }
        ]
      },
      {
        "mp3Url": [
          "https://d1u5p3l4wpay3k.cloudfront.net/dota2_gamepedia/8/89/Snip_manta_01.mp3"
        ],
        "mp3Text": "Oh, Manta! Hee hee hee hee!",
        "imgs": [
          {
            "img": "https://d1u5p3l4wpay3k.cloudfront.net/dota2_gamepedia/thumb/8/84/Manta_Style_icon.png/20px-Manta_Style_icon.png?version=3c4e36850b80d5091af6573e4c0dfd07",
            "name": "Manta Style (4800)"
          }
        ]
      },
      {
        "mp3Url": [
          "https://d1u5p3l4wpay3k.cloudfront.net/dota2_gamepedia/f/f0/Snip_manta_02.mp3"
        ],
        "mp3Text": "Oh, Manta! Ha ha ha ha!",
        "imgs": [
          {
            "img": "https://d1u5p3l4wpay3k.cloudfront.net/dota2_gamepedia/thumb/8/84/Manta_Style_icon.png/20px-Manta_Style_icon.png?version=3c4e36850b80d5091af6573e4c0dfd07",
            "name": "Manta Style (4800)"
          }
        ]
      },
      {
        "mp3Url": [
          "https://d1u5p3l4wpay3k.cloudfront.net/dota2_gamepedia/1/1a/Snip_manta_03.mp3"
        ],
        "mp3Text": "Firing squad!",
        "imgs": [
          {
            "img": "https://d1u5p3l4wpay3k.cloudfront.net/dota2_gamepedia/thumb/8/84/Manta_Style_icon.png/20px-Manta_Style_icon.png?version=3c4e36850b80d5091af6573e4c0dfd07",
            "name": "Manta Style (4800)"
          }
        ]
      },
      {
        "mp3Url": [
          "https://d1u5p3l4wpay3k.cloudfront.net/dota2_gamepedia/6/68/Snip_deso_01.mp3"
        ],
        "mp3Text": "Oh, Desolator!",
        "imgs": [
          {
            "img": "https://d1u5p3l4wpay3k.cloudfront.net/dota2_gamepedia/thumb/8/84/Desolator_icon.png/20px-Desolator_icon.png?version=6799c37495e122a7036267841f8d87ef",
            "name": "Desolator (3500)"
          }
        ]
      },
      {
        "mp3Url": [
          "https://d1u5p3l4wpay3k.cloudfront.net/dota2_gamepedia/d/de/Snip_deso_02.mp3"
        ],
        "mp3Text": "Ah, Desolator!",
        "imgs": [
          {
            "img": "https://d1u5p3l4wpay3k.cloudfront.net/dota2_gamepedia/thumb/8/84/Desolator_icon.png/20px-Desolator_icon.png?version=6799c37495e122a7036267841f8d87ef",
            "name": "Desolator (3500)"
          }
        ]
      },
      {
        "mp3Url": [
          "https://d1u5p3l4wpay3k.cloudfront.net/dota2_gamepedia/0/00/Snip_deso_03.mp3"
        ],
        "mp3Text": "Hm hm, armor piercing!",
        "imgs": [
          {
            "img": "https://d1u5p3l4wpay3k.cloudfront.net/dota2_gamepedia/thumb/8/84/Desolator_icon.png/20px-Desolator_icon.png?version=6799c37495e122a7036267841f8d87ef",
            "name": "Desolator (3500)"
          }
        ]
      },
      {
        "mp3Url": [
          "https://d1u5p3l4wpay3k.cloudfront.net/dota2_gamepedia/f/fb/Snip_purch_armor_01.mp3"
        ],
        "mp3Text": "It's sort of a full metal jacket.",
        "imgs": [
          {
            "img": "https://d1u5p3l4wpay3k.cloudfront.net/dota2_gamepedia/thumb/d/d3/Assault_Cuirass_icon.png/20px-Assault_Cuirass_icon.png?version=06ca3d5061f4dcff2d14667b4a6c37a3",
            "name": "Assault Cuirass (5250)"
          }
        ]
      },
      {
        "mp3Url": [
          "https://d1u5p3l4wpay3k.cloudfront.net/dota2_gamepedia/3/36/Snip_immort_01.mp3"
        ],
        "mp3Text": "Immortality!",
        "imgs": [
          {
            "img": "https://d1u5p3l4wpay3k.cloudfront.net/dota2_gamepedia/thumb/2/20/Aegis_of_the_Immortal_icon.png/20px-Aegis_of_the_Immortal_icon.png?version=d8a77a4fb2ee05916589a1fdfc85ff72",
            "name": "Aegis of the Immortal"
          }
        ]
      }
    ]
  },
  {
    "voices": [
      {
        "mp3Url": [
          "https://d1u5p3l4wpay3k.cloudfront.net/dota2_gamepedia/b/be/Snip_immort_02.mp3"
        ],
        "mp3Text": "Ha ha, bullet proof!",
        "imgs": [
          {
            "img": "https://d1u5p3l4wpay3k.cloudfront.net/dota2_gamepedia/thumb/2/20/Aegis_of_the_Immortal_icon.png/20px-Aegis_of_the_Immortal_icon.png?version=d8a77a4fb2ee05916589a1fdfc85ff72",
            "name": "Aegis of the Immortal"
          }
        ]
      }
    ]
  },
  {
    "headTitle": "Dying",
    "type": "title"
  },
  {
    "voices": [
      {
        "mp3Url": [
          "https://d1u5p3l4wpay3k.cloudfront.net/dota2_gamepedia/4/47/Snip_kill_blade_04.mp3"
        ],
        "mp3Text": "Inconceivable!"
      },
      {
        "mp3Url": [
          "https://d1u5p3l4wpay3k.cloudfront.net/dota2_gamepedia/e/e7/Snip_death_01.mp3"
        ],
        "mp3Text": "No! Guh!"
      },
      {
        "mp3Url": [
          "https://d1u5p3l4wpay3k.cloudfront.net/dota2_gamepedia/5/51/Snip_death_02.mp3"
        ],
        "mp3Text": "Cheap shot…yuh…"
      },
      {
        "mp3Url": [
          "https://d1u5p3l4wpay3k.cloudfront.net/dota2_gamepedia/6/62/Snip_death_03.mp3"
        ],
        "mp3Text": "You never hear the one that gets you."
      },
      {
        "mp3Url": [
          "https://d1u5p3l4wpay3k.cloudfront.net/dota2_gamepedia/0/04/Snip_death_04.mp3"
        ],
        "mp3Text": "Didn't think you had the brass!"
      },
      {
        "mp3Url": [
          "https://d1u5p3l4wpay3k.cloudfront.net/dota2_gamepedia/e/eb/Snip_death_05.mp3"
        ],
        "mp3Text": "Powder burns…uh…"
      },
      {
        "mp3Url": [
          "https://d1u5p3l4wpay3k.cloudfront.net/dota2_gamepedia/7/7f/Snip_death_06.mp3"
        ],
        "mp3Text": "A mortal wound…"
      },
      {
        "mp3Url": [
          "https://d1u5p3l4wpay3k.cloudfront.net/dota2_gamepedia/7/74/Snip_death_07.mp3"
        ],
        "mp3Text": "My chamber is empty."
      },
      {
        "mp3Url": [
          "https://d1u5p3l4wpay3k.cloudfront.net/dota2_gamepedia/7/7e/Snip_death_08.mp3"
        ],
        "mp3Text": "A parting shot."
      },
      {
        "mp3Url": [
          "https://d1u5p3l4wpay3k.cloudfront.net/dota2_gamepedia/a/a4/Snip_death_09.mp3"
        ],
        "mp3Text": "I go out guns blazing."
      },
      {
        "mp3Url": [
          "https://d1u5p3l4wpay3k.cloudfront.net/dota2_gamepedia/8/8f/Snip_death_10.mp3"
        ],
        "mp3Text": "Through and through…"
      },
      {
        "mp3Url": [
          "https://d1u5p3l4wpay3k.cloudfront.net/dota2_gamepedia/f/f7/Snip_death_11.mp3"
        ],
        "mp3Text": "Aw sheeeee-oooot."
      },
      {
        "mp3Url": [
          "https://d1u5p3l4wpay3k.cloudfront.net/dota2_gamepedia/9/9f/Snip_death_12.mp3"
        ],
        "mp3Text": "Exit wound…"
      }
    ]
  },
  {
    "headTitle": "Respawning",
    "type": "title"
  },
  {
    "voices": [
      {
        "mp3Url": [
          "https://d1u5p3l4wpay3k.cloudfront.net/dota2_gamepedia/1/11/Snip_respawn_01.mp3"
        ],
        "mp3Text": "That was a hell of a recoil."
      },
      {
        "mp3Url": [
          "https://d1u5p3l4wpay3k.cloudfront.net/dota2_gamepedia/7/71/Snip_respawn_02.mp3"
        ],
        "mp3Text": "Ah, reloaded."
      },
      {
        "mp3Url": [
          "https://d1u5p3l4wpay3k.cloudfront.net/dota2_gamepedia/9/9d/Snip_respawn_03.mp3"
        ],
        "mp3Text": "Another shot at victory."
      },
      {
        "mp3Url": [
          "https://d1u5p3l4wpay3k.cloudfront.net/dota2_gamepedia/6/6a/Snip_respawn_04.mp3"
        ],
        "mp3Text": "Huh, back at the shooting gallery."
      },
      {
        "mp3Url": [
          "https://d1u5p3l4wpay3k.cloudfront.net/dota2_gamepedia/4/4e/Snip_respawn_05.mp3"
        ],
        "mp3Text": "I'll stick to my guns."
      },
      {
        "mp3Url": [
          "https://d1u5p3l4wpay3k.cloudfront.net/dota2_gamepedia/8/8e/Snip_respawn_06.mp3"
        ],
        "mp3Text": "The shooting star returns!"
      },
      {
        "mp3Url": [
          "https://d1u5p3l4wpay3k.cloudfront.net/dota2_gamepedia/f/f5/Snip_respawn_07.mp3"
        ],
        "mp3Text": "Don't shoot, it's me."
      },
      {
        "mp3Url": [
          "https://d1u5p3l4wpay3k.cloudfront.net/dota2_gamepedia/2/22/Snip_respawn_08.mp3"
        ],
        "mp3Text": "Return fire!"
      },
      {
        "mp3Url": [
          "https://d1u5p3l4wpay3k.cloudfront.net/dota2_gamepedia/6/6b/Snip_respawn_09.mp3"
        ],
        "mp3Text": "Hm hm hm, my trigger finger's itching for vengeance!"
      },
      {
        "mp3Url": [
          "https://d1u5p3l4wpay3k.cloudfront.net/dota2_gamepedia/f/f3/Snip_respawn_10.mp3"
        ],
        "mp3Text": "Never could resist a long shot."
      },
      {
        "mp3Url": [
          "https://d1u5p3l4wpay3k.cloudfront.net/dota2_gamepedia/6/6f/Snip_respawn_11.mp3"
        ],
        "mp3Text": "Sniper reloaded!"
      }
    ]
  },
  {
    "text": "Reincarnating",
    "type": "subTitle"
  },
  {
    "voices": [
      {
        "mp3Url": [
          "https://d1u5p3l4wpay3k.cloudfront.net/dota2_gamepedia/0/07/Snip_laugh_08.mp3"
        ],
        "mp3Text": "Hee hee hee hee hee hee hee hee hee hee!"
      }
    ]
  },
  {
    "headTitle": "Bottling Runes",
    "type": "title"
  },
  {
    "voices": [
      {
        "mp3Url": [
          "https://d1u5p3l4wpay3k.cloudfront.net/dota2_gamepedia/d/dd/Snip_bottle_01.mp3"
        ],
        "mp3Text": "Saved for later."
      },
      {
        "mp3Url": [
          "https://d1u5p3l4wpay3k.cloudfront.net/dota2_gamepedia/2/22/Snip_bottle_02.mp3"
        ],
        "mp3Text": "This will come in handy."
      },
      {
        "mp3Url": [
          "https://d1u5p3l4wpay3k.cloudfront.net/dota2_gamepedia/f/f6/Snip_bottle_03.mp3"
        ],
        "mp3Text": "Just in case."
      }
    ]
  },
  {
    "voices": [
      {
        "mp3Url": [
          "https://d1u5p3l4wpay3k.cloudfront.net/dota2_gamepedia/0/0a/Snip_bottle_04.mp3"
        ],
        "mp3Text": "Jarate!"
      }
    ]
  },
  {
    "headTitle": "Activating runes",
    "type": "title"
  },
  {
    "imgUrl": "https://d1u5p3l4wpay3k.cloudfront.net/dota2_gamepedia/thumb/3/30/Arcane_Rune_minimap_icon.png/16px-Arcane_Rune_minimap_icon.png?version=280a8a1e2b8463bd66ddb7c5e919e442",
    "skillName": "Arcane Rune",
    "type": "rune"
  },
  {
    "voices": [
      {
        "mp3Url": [
          "https://d1u5p3l4wpay3k.cloudfront.net/dota2_gamepedia/b/b3/Snip_happy_03.mp3"
        ],
        "mp3Text": "Heyeah!"
      }
    ]
  },
  {
    "imgUrl": "https://d1u5p3l4wpay3k.cloudfront.net/dota2_gamepedia/thumb/c/c9/Bounty_Rune_minimap_icon.png/16px-Bounty_Rune_minimap_icon.png?version=e9045dc19a512c0fb0fad3a90a8d2e9a",
    "skillName": "Bounty Rune",
    "type": "rune"
  },
  {
    "voices": [
      {
        "mp3Url": [
          "https://d1u5p3l4wpay3k.cloudfront.net/dota2_gamepedia/7/7e/Snip_purch_03.mp3"
        ],
        "mp3Text": "Ah, this will come in handy."
      }
    ]
  },
  {
    "imgUrl": "https://d1u5p3l4wpay3k.cloudfront.net/dota2_gamepedia/thumb/7/77/Double_Damage_Rune_minimap_icon.png/16px-Double_Damage_Rune_minimap_icon.png?version=0812a173ad5eb93bf7bf91a07a4ba903",
    "skillName": "Double Damage Rune",
    "type": "rune"
  },
  {
    "voices": [
      {
        "mp3Url": [
          "https://d1u5p3l4wpay3k.cloudfront.net/dota2_gamepedia/0/04/Snip_doubdam_01.mp3"
        ],
        "mp3Text": "Double damage!"
      }
    ]
  },
  {
    "voices": [
      {
        "mp3Url": [
          "https://d1u5p3l4wpay3k.cloudfront.net/dota2_gamepedia/9/93/Snip_doubdam_02.mp3"
        ],
        "mp3Text": "Double action!"
      }
    ]
  },
  {
    "imgUrl": "https://d1u5p3l4wpay3k.cloudfront.net/dota2_gamepedia/thumb/7/7e/Haste_Rune_minimap_icon.png/16px-Haste_Rune_minimap_icon.png?version=2e1784dab99a3c8d178ebd0aeb867f23",
    "skillName": "Haste Rune",
    "type": "rune"
  },
  {
    "voices": [
      {
        "mp3Url": [
          "https://d1u5p3l4wpay3k.cloudfront.net/dota2_gamepedia/7/73/Snip_haste_01.mp3"
        ],
        "mp3Text": "Haste!"
      }
    ]
  },
  {
    "voices": [
      {
        "mp3Url": [
          "https://d1u5p3l4wpay3k.cloudfront.net/dota2_gamepedia/0/0b/Snip_haste_02.mp3"
        ],
        "mp3Text": "Off like a shot!"
      }
    ]
  },
  {
    "imgUrl": "https://d1u5p3l4wpay3k.cloudfront.net/dota2_gamepedia/thumb/1/10/Illusion_Rune_minimap_icon.png/16px-Illusion_Rune_minimap_icon.png?version=43c82cc02d3b4d0316ef268153a65ed5",
    "skillName": "Illusion Rune",
    "type": "rune"
  },
  {
    "voices": [
      {
        "mp3Url": [
          "https://d1u5p3l4wpay3k.cloudfront.net/dota2_gamepedia/b/b7/Snip_illus_01.mp3"
        ],
        "mp3Text": "Illusion!"
      }
    ]
  },
  {
    "voices": [
      {
        "mp3Url": [
          "https://d1u5p3l4wpay3k.cloudfront.net/dota2_gamepedia/0/05/Snip_illus_02.mp3"
        ],
        "mp3Text": "Parallax!"
      }
    ]
  },
  {
    "imgUrl": "https://d1u5p3l4wpay3k.cloudfront.net/dota2_gamepedia/thumb/0/09/Invisibility_Rune_minimap_icon.png/16px-Invisibility_Rune_minimap_icon.png?version=4d5cd179b09fab37a749449924197d52",
    "skillName": "Invisibility Rune",
    "type": "rune"
  },
  {
    "voices": [
      {
        "mp3Url": [
          "https://d1u5p3l4wpay3k.cloudfront.net/dota2_gamepedia/5/59/Snip_invis_01.mp3"
        ],
        "mp3Text": "Invisibility!"
      },
      {
        "mp3Url": [
          "https://d1u5p3l4wpay3k.cloudfront.net/dota2_gamepedia/5/56/Snip_invis_02.mp3"
        ],
        "mp3Text": "Out of visual range! He he he he!"
      }
    ]
  },
  {
    "imgUrl": "https://d1u5p3l4wpay3k.cloudfront.net/dota2_gamepedia/thumb/7/77/Regeneration_Rune_minimap_icon.png/16px-Regeneration_Rune_minimap_icon.png?version=31dd69fac564f0f9be4421d7bf8c60f4",
    "skillName": "Regeneration Rune",
    "type": "rune"
  },
  {
    "voices": [
      {
        "mp3Url": [
          "https://d1u5p3l4wpay3k.cloudfront.net/dota2_gamepedia/9/9e/Snip_regen_01.mp3"
        ],
        "mp3Text": "Regeneration!"
      }
    ]
  },
  {
    "voices": [
      {
        "mp3Url": [
          "https://d1u5p3l4wpay3k.cloudfront.net/dota2_gamepedia/e/e4/Snip_regen_02.mp3"
        ],
        "mp3Text": "Fixed my sights!"
      }
    ]
  },
  {
    "headTitle": "Ability on cooldown",
    "type": "title"
  },
  {
    "text": "First attempt within 10 seconds",
    "type": "small"
  },
  {
    "voices": [
      {
        "mp3Url": [
          "https://d1u5p3l4wpay3k.cloudfront.net/dota2_gamepedia/c/c6/Snip_notyet_01.mp3"
        ],
        "mp3Text": "Not yet."
      },
      {
        "mp3Url": [
          "https://d1u5p3l4wpay3k.cloudfront.net/dota2_gamepedia/e/e0/Snip_notyet_01a.mp3"
        ],
        "mp3Text": "Not yet."
      },
      {
        "mp3Url": [
          "https://d1u5p3l4wpay3k.cloudfront.net/dota2_gamepedia/0/00/Snip_notyet_02.mp3"
        ],
        "mp3Text": "I'm not ready."
      },
      {
        "mp3Url": [
          "https://d1u5p3l4wpay3k.cloudfront.net/dota2_gamepedia/c/cb/Snip_notyet_02a.mp3"
        ],
        "mp3Text": "I'm not ready."
      },
      {
        "mp3Url": [
          "https://d1u5p3l4wpay3k.cloudfront.net/dota2_gamepedia/3/35/Snip_notyet_03.mp3"
        ],
        "mp3Text": "It's not time yet."
      },
      {
        "mp3Url": [
          "https://d1u5p3l4wpay3k.cloudfront.net/dota2_gamepedia/b/b8/Snip_notyet_03a.mp3"
        ],
        "mp3Text": "It's not time."
      }
    ]
  },
  {
    "text": "Second attempt within 10 seconds",
    "type": "small"
  },
  {
    "voices": [
      {
        "mp3Url": [
          "https://d1u5p3l4wpay3k.cloudfront.net/dota2_gamepedia/c/ce/Snip_notyet_04.mp3"
        ],
        "mp3Text": "Not yet."
      },
      {
        "mp3Url": [
          "https://d1u5p3l4wpay3k.cloudfront.net/dota2_gamepedia/9/9d/Snip_notyet_05.mp3"
        ],
        "mp3Text": "I'm not ready."
      },
      {
        "mp3Url": [
          "https://d1u5p3l4wpay3k.cloudfront.net/dota2_gamepedia/8/8c/Snip_notyet_06.mp3"
        ],
        "mp3Text": "It's not time yet."
      }
    ]
  },
  {
    "text": "Third and more attempts within 10 seconds",
    "type": "small"
  },
  {
    "voices": [
      {
        "mp3Url": [
          "https://d1u5p3l4wpay3k.cloudfront.net/dota2_gamepedia/4/45/Snip_notyet_07.mp3"
        ],
        "mp3Text": "Not yet."
      },
      {
        "mp3Url": [
          "https://d1u5p3l4wpay3k.cloudfront.net/dota2_gamepedia/5/55/Snip_notyet_08.mp3"
        ],
        "mp3Text": "I'm not ready."
      },
      {
        "mp3Url": [
          "https://d1u5p3l4wpay3k.cloudfront.net/dota2_gamepedia/2/2c/Snip_notyet_09.mp3"
        ],
        "mp3Text": "It's not time yet."
      }
    ]
  },
  {
    "headTitle": "Not enough mana",
    "type": "title"
  },
  {
    "text": "First attempt within 10 seconds",
    "type": "small"
  },
  {
    "voices": [
      {
        "mp3Url": [
          "https://d1u5p3l4wpay3k.cloudfront.net/dota2_gamepedia/5/5e/Snip_nomana_01.mp3"
        ],
        "mp3Text": "Out of mana."
      },
      {
        "mp3Url": [
          "https://d1u5p3l4wpay3k.cloudfront.net/dota2_gamepedia/3/3c/Snip_nomana_01a.mp3"
        ],
        "mp3Text": "Out of mana."
      },
      {
        "mp3Url": [
          "https://d1u5p3l4wpay3k.cloudfront.net/dota2_gamepedia/7/7b/Snip_nomana_02.mp3"
        ],
        "mp3Text": "No mana."
      },
      {
        "mp3Url": [
          "https://d1u5p3l4wpay3k.cloudfront.net/dota2_gamepedia/b/bb/Snip_nomana_02a.mp3"
        ],
        "mp3Text": "No mana."
      },
      {
        "mp3Url": [
          "https://d1u5p3l4wpay3k.cloudfront.net/dota2_gamepedia/6/6f/Snip_nomana_03.mp3"
        ],
        "mp3Text": "Not enough mana."
      },
      {
        "mp3Url": [
          "https://d1u5p3l4wpay3k.cloudfront.net/dota2_gamepedia/2/29/Snip_nomana_03a.mp3"
        ],
        "mp3Text": "Not enough mana."
      }
    ]
  },
  {
    "text": "Second attempt within 10 seconds",
    "type": "small"
  },
  {
    "voices": [
      {
        "mp3Url": [
          "https://d1u5p3l4wpay3k.cloudfront.net/dota2_gamepedia/8/8a/Snip_nomana_04.mp3"
        ],
        "mp3Text": "Out of mana."
      },
      {
        "mp3Url": [
          "https://d1u5p3l4wpay3k.cloudfront.net/dota2_gamepedia/d/d1/Snip_nomana_05.mp3"
        ],
        "mp3Text": "No mana."
      },
      {
        "mp3Url": [
          "https://d1u5p3l4wpay3k.cloudfront.net/dota2_gamepedia/9/9e/Snip_nomana_06.mp3"
        ],
        "mp3Text": "Not enough mana."
      },
      {
        "mp3Url": [
          "https://d1u5p3l4wpay3k.cloudfront.net/dota2_gamepedia/b/bf/Snip_nomana_10.mp3"
        ],
        "mp3Text": "You're jumping the gun."
      }
    ]
  },
  {
    "text": "Third and more attempts within 10 seconds",
    "type": "small"
  },
  {
    "voices": [
      {
        "mp3Url": [
          "https://d1u5p3l4wpay3k.cloudfront.net/dota2_gamepedia/9/9c/Snip_nomana_07.mp3"
        ],
        "mp3Text": "Out of mana."
      },
      {
        "mp3Url": [
          "https://d1u5p3l4wpay3k.cloudfront.net/dota2_gamepedia/6/66/Snip_nomana_08.mp3"
        ],
        "mp3Text": "No mana."
      },
      {
        "mp3Url": [
          "https://d1u5p3l4wpay3k.cloudfront.net/dota2_gamepedia/2/24/Snip_nomana_09.mp3"
        ],
        "mp3Text": "Not enough mana."
      }
    ]
  },
  {
    "headTitle": "Taking damage",
    "type": "title"
  },
  {
    "voices": [
      {
        "mp3Url": [
          "https://d1u5p3l4wpay3k.cloudfront.net/dota2_gamepedia/9/97/Snip_pain_01.mp3"
        ],
        "mp3Text": "Erk!"
      },
      {
        "mp3Url": [
          "https://d1u5p3l4wpay3k.cloudfront.net/dota2_gamepedia/9/9e/Snip_pain_02.mp3"
        ],
        "mp3Text": "Doh!"
      },
      {
        "mp3Url": [
          "https://d1u5p3l4wpay3k.cloudfront.net/dota2_gamepedia/4/43/Snip_pain_03.mp3"
        ],
        "mp3Text": "Eh!"
      },
      {
        "mp3Url": [
          "https://d1u5p3l4wpay3k.cloudfront.net/dota2_gamepedia/1/10/Snip_pain_04.mp3"
        ],
        "mp3Text": "Eeh"
      },
      {
        "mp3Url": [
          "https://d1u5p3l4wpay3k.cloudfront.net/dota2_gamepedia/8/81/Snip_pain_05.mp3"
        ],
        "mp3Text": "Oh!"
      },
      {
        "mp3Url": [
          "https://d1u5p3l4wpay3k.cloudfront.net/dota2_gamepedia/8/8d/Snip_pain_06.mp3"
        ],
        "mp3Text": "Ah!"
      },
      {
        "mp3Url": [
          "https://d1u5p3l4wpay3k.cloudfront.net/dota2_gamepedia/f/fa/Snip_pain_07.mp3"
        ],
        "mp3Text": "Tak!"
      },
      {
        "mp3Url": [
          "https://d1u5p3l4wpay3k.cloudfront.net/dota2_gamepedia/e/e0/Snip_pain_08.mp3"
        ],
        "mp3Text": "Ah!"
      },
      {
        "mp3Url": [
          "https://d1u5p3l4wpay3k.cloudfront.net/dota2_gamepedia/b/bf/Snip_pain_09.mp3"
        ],
        "mp3Text": "Eeh."
      }
    ]
  },
  {
    "voices": [
      {
        "mp3Url": [
          "https://d1u5p3l4wpay3k.cloudfront.net/dota2_gamepedia/0/05/Snip_underattack_01.mp3"
        ],
        "mp3Text": "I'm under attack!"
      }
    ]
  },
  {
    "headTitle": "Selecting",
    "type": "title"
  },
  {
    "text": "5 consecutive clicks on the hero",
    "type": "small"
  },
  {
    "voices": [
      {
        "mp3Url": [
          "https://d1u5p3l4wpay3k.cloudfront.net/dota2_gamepedia/b/b4/Snip_tf2_06.mp3"
        ],
        "mp3Text": "Professionals have standards."
      },
      {
        "mp3Url": [
          "https://d1u5p3l4wpay3k.cloudfront.net/dota2_gamepedia/0/09/Snip_tf2_08.mp3"
        ],
        "mp3Text": "As long as there are two heroes left on the battlefield, someone is gonna want someone dead."
      },
      {
        "mp3Url": [
          "https://d1u5p3l4wpay3k.cloudfront.net/dota2_gamepedia/a/ad/Snip_rare_01.mp3"
        ],
        "mp3Text": "There's not much wrong that killing you wouldn't fix."
      },
      {
        "mp3Url": [
          "https://d1u5p3l4wpay3k.cloudfront.net/dota2_gamepedia/7/76/Snip_rare_02.mp3"
        ],
        "mp3Text": "Killing is the last resort, true. But the other resorts don't even have a pool."
      },
      {
        "mp3Url": [
          "https://d1u5p3l4wpay3k.cloudfront.net/dota2_gamepedia/5/50/Snip_rare_03.mp3"
        ],
        "mp3Text": "Dying is easy. Here, let me show you."
      },
      {
        "mp3Url": [
          "https://d1u5p3l4wpay3k.cloudfront.net/dota2_gamepedia/7/7f/Snip_rare_04.mp3"
        ],
        "mp3Text": "Why am I smiling? This is what trigger-happy looks like."
      }
    ]
  },
  {
    "headTitle": "Chat responses",
    "type": "title"
  },
  {
    "text": "Thanking",
    "type": "subTitle"
  },
  {
    "voices": [
      {
        "mp3Url": [
          "https://d1u5p3l4wpay3k.cloudfront.net/dota2_gamepedia/5/57/Snip_thanks_01.mp3"
        ],
        "mp3Text": "Thanks!"
      },
      {
        "mp3Url": [
          "https://d1u5p3l4wpay3k.cloudfront.net/dota2_gamepedia/4/4a/Snip_thanks_02.mp3"
        ],
        "mp3Text": "I owe ya one."
      }
    ]
  },
  {
    "text": "Laughing",
    "type": "subTitle"
  },
  {
    "voices": [
      {
        "mp3Url": [
          "https://d1u5p3l4wpay3k.cloudfront.net/dota2_gamepedia/3/3d/Snip_laugh_01.mp3"
        ],
        "mp3Text": "Oh ho ho haw!"
      },
      {
        "mp3Url": [
          "https://d1u5p3l4wpay3k.cloudfront.net/dota2_gamepedia/b/b3/Snip_laugh_02.mp3"
        ],
        "mp3Text": "Heh heh heh!"
      },
      {
        "mp3Url": [
          "https://d1u5p3l4wpay3k.cloudfront.net/dota2_gamepedia/3/31/Snip_laugh_03.mp3"
        ],
        "mp3Text": "Ha ha ha!"
      },
      {
        "mp3Url": [
          "https://d1u5p3l4wpay3k.cloudfront.net/dota2_gamepedia/0/03/Snip_laugh_04.mp3"
        ],
        "mp3Text": "Heh heh hee hee hee."
      },
      {
        "mp3Url": [
          "https://d1u5p3l4wpay3k.cloudfront.net/dota2_gamepedia/d/d6/Snip_laugh_05.mp3"
        ],
        "mp3Text": "Ho ho ho!"
      },
      {
        "mp3Url": [
          "https://d1u5p3l4wpay3k.cloudfront.net/dota2_gamepedia/4/46/Snip_laugh_06.mp3"
        ],
        "mp3Text": "Ha ha!"
      },
      {
        "mp3Url": [
          "https://d1u5p3l4wpay3k.cloudfront.net/dota2_gamepedia/1/1f/Snip_laugh_07.mp3"
        ],
        "mp3Text": "Ha ha ha ha ha!"
      },
      {
        "mp3Url": [
          "https://d1u5p3l4wpay3k.cloudfront.net/dota2_gamepedia/0/07/Snip_laugh_08.mp3"
        ],
        "mp3Text": "Hee hee hee hee hee hee hee hee hee hee!"
      },
      {
        "mp3Url": [
          "https://d1u5p3l4wpay3k.cloudfront.net/dota2_gamepedia/7/72/Snip_laugh_09.mp3"
        ],
        "mp3Text": "Hoo hoo hoo!"
      }
    ]
  },
  {
    "headTitle": "Match end",
    "type": "title"
  },
  {
    "text": "Won",
    "type": "middle"
  },
  {
    "voices": [
      {
        "mp3Url": [
          "https://d1u5p3l4wpay3k.cloudfront.net/dota2_gamepedia/3/32/Snip_win_01.mp3"
        ],
        "mp3Text": "Yes!"
      },
      {
        "mp3Url": [
          "https://d1u5p3l4wpay3k.cloudfront.net/dota2_gamepedia/9/95/Snip_win_02.mp3"
        ],
        "mp3Text": "Victory!"
      },
      {
        "mp3Url": [
          "https://d1u5p3l4wpay3k.cloudfront.net/dota2_gamepedia/9/9d/Snip_win_03.mp3"
        ],
        "mp3Text": "He shoots, he scores!"
      }
    ]
  },
  {
    "text": "Lost",
    "type": "middle"
  },
  {
    "voices": [
      {
        "mp3Url": [
          "https://d1u5p3l4wpay3k.cloudfront.net/dota2_gamepedia/f/f1/Snip_lose_01.mp3"
        ],
        "mp3Text": "Noooo!"
      },
      {
        "mp3Url": [
          "https://d1u5p3l4wpay3k.cloudfront.net/dota2_gamepedia/3/3a/Snip_lose_02.mp3"
        ],
        "mp3Text": "Defeated!"
      },
      {
        "mp3Url": [
          "https://d1u5p3l4wpay3k.cloudfront.net/dota2_gamepedia/f/f2/Snip_lose_03.mp3"
        ],
        "mp3Text": "Dah! There goes the whole shootin' match!"
      }
    ]
  },
  {
    "headTitle": "Cosmetic item drop",
    "type": "title"
  },
  {
    "text": "Common",
    "type": "middle"
  },
  {
    "voices": [
      {
        "mp3Url": [
          "https://d1u5p3l4wpay3k.cloudfront.net/dota2_gamepedia/c/ca/Snip_happy_01.mp3"
        ],
        "mp3Text": "Ah!"
      }
    ]
  },
  {
    "text": "Uncommon",
    "type": "middle"
  },
  {
    "voices": [
      {
        "mp3Url": [
          "https://d1u5p3l4wpay3k.cloudfront.net/dota2_gamepedia/4/4d/Snip_kill_arrow_01.mp3"
        ],
        "mp3Text": "Oh, how cute!"
      }
    ]
  },
  {
    "text": "Rare and higher",
    "type": "middle"
  },
  {
    "voices": [
      {
        "mp3Url": [
          "https://d1u5p3l4wpay3k.cloudfront.net/dota2_gamepedia/b/b3/Snip_happy_03.mp3"
        ],
        "mp3Text": "Heyeah!"
      }
    ]
  },
  {
    "headTitle": "Misc",
    "type": "title"
  },
  {
    "text": "Wizard",
    "type": "subTitle"
  },
  {
    "voices": [
      {
        "mp3Url": [
          "https://d1u5p3l4wpay3k.cloudfront.net/dota2_gamepedia/b/b3/Snip_shitwiz_01.mp3"
        ],
        "mp3Text": "!"
      },
      {
        "mp3Url": [
          "https://d1u5p3l4wpay3k.cloudfront.net/dota2_gamepedia/d/d3/Snip_crumwiz_01.mp3"
        ],
        "mp3Text": "Crummy wizard!"
      }
    ]
  },
  {
    "text": "Anger",
    "type": "subTitle"
  },
  {
    "voices": [
      {
        "mp3Url": [
          "https://d1u5p3l4wpay3k.cloudfront.net/dota2_gamepedia/b/b3/Snip_anger_02.mp3"
        ],
        "mp3Text": "Dope!"
      },
      {
        "mp3Url": [
          "https://d1u5p3l4wpay3k.cloudfront.net/dota2_gamepedia/b/b4/Snip_anger_03.mp3"
        ],
        "mp3Text": "Gad!"
      },
      {
        "mp3Url": [
          "https://d1u5p3l4wpay3k.cloudfront.net/dota2_gamepedia/3/33/Snip_anger_04.mp3"
        ],
        "mp3Text": "Doh jah fft!"
      },
      {
        "mp3Url": [
          "https://d1u5p3l4wpay3k.cloudfront.net/dota2_gamepedia/c/c4/Snip_anger_05.mp3"
        ],
        "mp3Text": "Ah!"
      },
      {
        "mp3Url": [
          "https://d1u5p3l4wpay3k.cloudfront.net/dota2_gamepedia/2/26/Snip_anger_06.mp3"
        ],
        "mp3Text": "Grrrrr!"
      }
    ]
  },
  {
    "text": "Happy",
    "type": "subTitle"
  },
  {
    "voices": [
      {
        "mp3Url": [
          "https://d1u5p3l4wpay3k.cloudfront.net/dota2_gamepedia/4/47/Snip_happy_02.mp3"
        ],
        "mp3Text": "Ahhh!"
      }
    ]
  }
]