[
  {
    "actorImg": "https://d1u5p3l4wpay3k.cloudfront.net/dota2_gamepedia/thumb/d/dd/Nolan_North.jpg/100px-Nolan_North.jpg?version=ae280a988ef0cc5e1ab07ac7f46ced7f",
    "actor": "Nolan North",
    "actorUrl": "http://en.wikipedia.org/wiki/Nolan_North",
    "heroAvater": "https://d1u5p3l4wpay3k.cloudfront.net/dota2_gamepedia/thumb/a/a2/Troll_Warlord_minimap_icon.png/20px-Troll_Warlord_minimap_icon.png?version=26aac0aac38d2d36ad5addd7ff8abd11",
    "heroName": "Troll Warlord",
    "avaterMain": "http://www.dota2.com.cn/images/heroes/troll_warlord_full.png",
    "primaryAttribute": "Agility",
    "longAvatar": "https://coding.net/u/dovahkiin/p/tempData/git/raw/master/avatar/trollwarlord.png",
    "cnName": "巨魔战将",
    "bannerImg": "https://cdn.max-c.com/app/dota2/troll_warlord@3x.png"
  },
  {
    "headTitle": "Loadout",
    "type": "title"
  },
  {
    "type": "voice",
    "mp3Url": [
      "https://coding.net/u/dovahkiin/p/tempData/git/raw/master/allmp3/Troll%20Warlord/Troll_spawn_01.mp3"
    ],
    "mp3Text": "Troll Warlord."
  },
  {
    "type": "voice",
    "mp3Url": [
      "https://coding.net/u/dovahkiin/p/tempData/git/raw/master/allmp3/Troll%20Warlord/Troll_spawn_02.mp3"
    ],
    "mp3Text": "Jah'rakal!"
  },
  {
    "type": "voice",
    "mp3Url": [
      "https://coding.net/u/dovahkiin/p/tempData/git/raw/master/allmp3/Troll%20Warlord/Troll_spawn_03.mp3"
    ],
    "mp3Text": "All hail the Lord of Trolls."
  },
  {
    "type": "voice",
    "mp3Url": [
      "https://coding.net/u/dovahkiin/p/tempData/git/raw/master/allmp3/Troll%20Warlord/Troll_spawn_04.mp3"
    ],
    "mp3Text": "The strong shall eat the weak."
  },
  {
    "type": "voice",
    "mp3Url": [
      "https://coding.net/u/dovahkiin/p/tempData/git/raw/master/allmp3/Troll%20Warlord/Troll_spawn_05.mp3"
    ],
    "mp3Text": "All will bleed."
  },
  {
    "type": "voice",
    "mp3Url": [
      "https://coding.net/u/dovahkiin/p/tempData/git/raw/master/allmp3/Troll%20Warlord/Troll_spawn_06.mp3"
    ],
    "mp3Text": "My hate shall burn you down."
  },
  {
    "type": "voice",
    "mp3Url": [
      "https://coding.net/u/dovahkiin/p/tempData/git/raw/master/allmp3/Troll%20Warlord/Troll_move_07.mp3"
    ],
    "mp3Text": "These blades are too dry."
  },
  {
    "type": "voice",
    "mp3Url": [
      "https://coding.net/u/dovahkiin/p/tempData/git/raw/master/allmp3/Troll%20Warlord/Troll_move_12.mp3"
    ],
    "mp3Text": "My axes thirst."
  },
  {
    "type": "voice",
    "mp3Url": [
      "https://coding.net/u/dovahkiin/p/tempData/git/raw/master/allmp3/Troll%20Warlord/Troll_cast_03.mp3"
    ],
    "mp3Text": "I'm coming for you."
  },
  {
    "type": "voice",
    "mp3Url": [
      "https://coding.net/u/dovahkiin/p/tempData/git/raw/master/allmp3/Troll%20Warlord/Troll_beserker_03.mp3"
    ],
    "mp3Text": "Feed my blades."
  },
  {
    "type": "voice",
    "mp3Url": [
      "https://coding.net/u/dovahkiin/p/tempData/git/raw/master/allmp3/Troll%20Warlord/Troll_fervor_05.mp3"
    ],
    "mp3Text": "Come at me."
  },
  {
    "type": "voice",
    "mp3Url": [
      "https://coding.net/u/dovahkiin/p/tempData/git/raw/master/allmp3/Troll%20Warlord/Troll_respawn_09.mp3"
    ],
    "mp3Text": "I live to fight."
  },
  {
    "headTitle": "Drafting",
    "type": "title"
  },
  {
    "text": "Picked",
    "type": "middle"
  },
  {
    "type": "voice",
    "mp3Url": [
      "https://coding.net/u/dovahkiin/p/tempData/git/raw/master/allmp3/Troll%20Warlord/Troll_spawn_01.mp3"
    ],
    "mp3Text": "Troll Warlord."
  },
  {
    "text": "Banned",
    "type": "middle"
  },
  {
    "type": "voice",
    "mp3Url": [
      "https://coding.net/u/dovahkiin/p/tempData/git/raw/master/allmp3/Troll%20Warlord/Troll_anger_03.mp3"
    ],
    "mp3Text": "Arh kill you all."
  },
  {
    "headTitle": "Entering battle",
    "type": "title"
  },
  {
    "type": "voice",
    "mp3Url": [
      "https://coding.net/u/dovahkiin/p/tempData/git/raw/master/allmp3/Troll%20Warlord/Troll_spawn_01.mp3"
    ],
    "mp3Text": "Troll Warlord."
  },
  {
    "type": "voice",
    "mp3Url": [
      "https://coding.net/u/dovahkiin/p/tempData/git/raw/master/allmp3/Troll%20Warlord/Troll_spawn_02.mp3"
    ],
    "mp3Text": "Jah'rakal!"
  },
  {
    "type": "voice",
    "mp3Url": [
      "https://coding.net/u/dovahkiin/p/tempData/git/raw/master/allmp3/Troll%20Warlord/Troll_spawn_03.mp3"
    ],
    "mp3Text": "All hail the Lord of Trolls."
  },
  {
    "type": "voice",
    "mp3Url": [
      "https://coding.net/u/dovahkiin/p/tempData/git/raw/master/allmp3/Troll%20Warlord/Troll_spawn_04.mp3"
    ],
    "mp3Text": "The strong shall eat the weak."
  },
  {
    "type": "voice",
    "mp3Url": [
      "https://coding.net/u/dovahkiin/p/tempData/git/raw/master/allmp3/Troll%20Warlord/Troll_spawn_05.mp3"
    ],
    "mp3Text": "All will bleed."
  },
  {
    "type": "voice",
    "mp3Url": [
      "https://coding.net/u/dovahkiin/p/tempData/git/raw/master/allmp3/Troll%20Warlord/Troll_spawn_06.mp3"
    ],
    "mp3Text": "My hate shall burn you down."
  },
  {
    "headTitle": "Taunting",
    "type": "title"
  },
  {
    "type": "voice",
    "mp3Url": [
      "https://coding.net/u/dovahkiin/p/tempData/git/raw/master/allmp3/Troll%20Warlord/Troll_inthebag_01.mp3"
    ],
    "mp3Text": "All you trolls pay attention when I tell you, this one is in the bag."
  },
  {
    "headTitle": "Beginning battle",
    "type": "title"
  },
  {
    "type": "voice",
    "mp3Url": [
      "https://coding.net/u/dovahkiin/p/tempData/git/raw/master/allmp3/Troll%20Warlord/Troll_begin_01.mp3"
    ],
    "mp3Text": "The bell tolls for the lord of trolls."
  },
  {
    "headTitle": "Moving",
    "type": "title"
  },
  {
    "type": "voice",
    "mp3Url": [
      "https://coding.net/u/dovahkiin/p/tempData/git/raw/master/allmp3/Troll%20Warlord/Troll_move_01.mp3"
    ],
    "mp3Text": "Heahuh."
  },
  {
    "type": "voice",
    "mp3Url": [
      "https://coding.net/u/dovahkiin/p/tempData/git/raw/master/allmp3/Troll%20Warlord/Troll_move_02.mp3"
    ],
    "mp3Text": "Yes."
  },
  {
    "type": "voice",
    "mp3Url": [
      "https://coding.net/u/dovahkiin/p/tempData/git/raw/master/allmp3/Troll%20Warlord/Troll_move_03.mp3"
    ],
    "mp3Text": "Yes."
  },
  {
    "type": "voice",
    "mp3Url": [
      "https://coding.net/u/dovahkiin/p/tempData/git/raw/master/allmp3/Troll%20Warlord/Troll_move_04.mp3"
    ],
    "mp3Text": "To the massacre."
  },
  {
    "type": "voice",
    "mp3Url": [
      "https://coding.net/u/dovahkiin/p/tempData/git/raw/master/allmp3/Troll%20Warlord/Troll_move_05.mp3"
    ],
    "mp3Text": "Aghast."
  },
  {
    "type": "voice",
    "mp3Url": [
      "https://coding.net/u/dovahkiin/p/tempData/git/raw/master/allmp3/Troll%20Warlord/Troll_move_06.mp3"
    ],
    "mp3Text": "There are no innocents."
  },
  {
    "type": "voice",
    "mp3Url": [
      "https://coding.net/u/dovahkiin/p/tempData/git/raw/master/allmp3/Troll%20Warlord/Troll_move_07.mp3"
    ],
    "mp3Text": "These blades are too dry."
  },
  {
    "type": "voice",
    "mp3Url": [
      "https://coding.net/u/dovahkiin/p/tempData/git/raw/master/allmp3/Troll%20Warlord/Troll_move_08.mp3"
    ],
    "mp3Text": "My steel shall drink."
  },
  {
    "type": "voice",
    "mp3Url": [
      "https://coding.net/u/dovahkiin/p/tempData/git/raw/master/allmp3/Troll%20Warlord/Troll_move_09.mp3"
    ],
    "mp3Text": "I hear sniveling."
  },
  {
    "type": "voice",
    "mp3Url": [
      "https://coding.net/u/dovahkiin/p/tempData/git/raw/master/allmp3/Troll%20Warlord/Troll_move_10.mp3"
    ],
    "mp3Text": "No agony enough."
  },
  {
    "type": "voice",
    "mp3Url": [
      "https://coding.net/u/dovahkiin/p/tempData/git/raw/master/allmp3/Troll%20Warlord/Troll_move_11.mp3"
    ],
    "mp3Text": "Faster, faster."
  },
  {
    "type": "voice",
    "mp3Url": [
      "https://coding.net/u/dovahkiin/p/tempData/git/raw/master/allmp3/Troll%20Warlord/Troll_move_12.mp3"
    ],
    "mp3Text": "My axes thirst."
  },
  {
    "type": "voice",
    "mp3Url": [
      "https://coding.net/u/dovahkiin/p/tempData/git/raw/master/allmp3/Troll%20Warlord/Troll_move_13.mp3"
    ],
    "mp3Text": "Trolling for victims."
  },
  {
    "type": "voice",
    "mp3Url": [
      "https://coding.net/u/dovahkiin/p/tempData/git/raw/master/allmp3/Troll%20Warlord/Troll_move_14.mp3"
    ],
    "mp3Text": "Don't cross my path."
  },
  {
    "type": "voice",
    "mp3Url": [
      "https://coding.net/u/dovahkiin/p/tempData/git/raw/master/allmp3/Troll%20Warlord/Troll_move_15.mp3"
    ],
    "mp3Text": "They'll rue the day."
  },
  {
    "headTitle": "Attacking",
    "type": "title"
  },
  {
    "type": "voice",
    "mp3Url": [
      "https://coding.net/u/dovahkiin/p/tempData/git/raw/master/allmp3/Troll%20Warlord/Troll_attack_01.mp3"
    ],
    "mp3Text": "Attack!"
  },
  {
    "type": "voice",
    "mp3Url": [
      "https://coding.net/u/dovahkiin/p/tempData/git/raw/master/allmp3/Troll%20Warlord/Troll_attack_02.mp3"
    ],
    "mp3Text": "Attack!"
  },
  {
    "type": "voice",
    "mp3Url": [
      "https://coding.net/u/dovahkiin/p/tempData/git/raw/master/allmp3/Troll%20Warlord/Troll_attack_03.mp3"
    ],
    "mp3Text": "Fools."
  },
  {
    "type": "voice",
    "mp3Url": [
      "https://coding.net/u/dovahkiin/p/tempData/git/raw/master/allmp3/Troll%20Warlord/Troll_attack_04.mp3"
    ],
    "mp3Text": "Maddening."
  },
  {
    "type": "voice",
    "mp3Url": [
      "https://coding.net/u/dovahkiin/p/tempData/git/raw/master/allmp3/Troll%20Warlord/Troll_attack_05.mp3"
    ],
    "mp3Text": "Deadly."
  },
  {
    "type": "voice",
    "mp3Url": [
      "https://coding.net/u/dovahkiin/p/tempData/git/raw/master/allmp3/Troll%20Warlord/Troll_attack_06.mp3"
    ],
    "mp3Text": "You deserve it."
  },
  {
    "type": "voice",
    "mp3Url": [
      "https://coding.net/u/dovahkiin/p/tempData/git/raw/master/allmp3/Troll%20Warlord/Troll_attack_07.mp3"
    ],
    "mp3Text": "Hate warms me."
  },
  {
    "type": "voice",
    "mp3Url": [
      "https://coding.net/u/dovahkiin/p/tempData/git/raw/master/allmp3/Troll%20Warlord/Troll_attack_08.mp3"
    ],
    "mp3Text": "My steel gorges."
  },
  {
    "type": "voice",
    "mp3Url": [
      "https://coding.net/u/dovahkiin/p/tempData/git/raw/master/allmp3/Troll%20Warlord/Troll_attack_09.mp3"
    ],
    "mp3Text": "Blood spurts!"
  },
  {
    "type": "voice",
    "mp3Url": [
      "https://coding.net/u/dovahkiin/p/tempData/git/raw/master/allmp3/Troll%20Warlord/Troll_attack_10.mp3"
    ],
    "mp3Text": "Gutteral spray!"
  },
  {
    "type": "voice",
    "mp3Url": [
      "https://coding.net/u/dovahkiin/p/tempData/git/raw/master/allmp3/Troll%20Warlord/Troll_attack_11.mp3"
    ],
    "mp3Text": "Murderous."
  },
  {
    "type": "voice",
    "mp3Url": [
      "https://coding.net/u/dovahkiin/p/tempData/git/raw/master/allmp3/Troll%20Warlord/Troll_attack_12.mp3"
    ],
    "mp3Text": "Die faster."
  },
  {
    "type": "voice",
    "mp3Url": [
      "https://coding.net/u/dovahkiin/p/tempData/git/raw/master/allmp3/Troll%20Warlord/Troll_attack_13.mp3"
    ],
    "mp3Text": "I peel back your uglies."
  },
  {
    "type": "voice",
    "mp3Url": [
      "https://coding.net/u/dovahkiin/p/tempData/git/raw/master/allmp3/Troll%20Warlord/Troll_attack_14.mp3"
    ],
    "mp3Text": "Please do feed the trolls."
  },
  {
    "type": "voice",
    "mp3Url": [
      "https://coding.net/u/dovahkiin/p/tempData/git/raw/master/allmp3/Troll%20Warlord/Troll_attack_15.mp3"
    ],
    "mp3Text": "Here's axe in your eye."
  },
  {
    "headTitle": "Ordering a spell cast",
    "type": "title"
  },
  {
    "type": "voice",
    "mp3Url": [
      "https://coding.net/u/dovahkiin/p/tempData/git/raw/master/allmp3/Troll%20Warlord/Troll_cast_01.mp3"
    ],
    "mp3Text": "Your future is short."
  },
  {
    "type": "voice",
    "mp3Url": [
      "https://coding.net/u/dovahkiin/p/tempData/git/raw/master/allmp3/Troll%20Warlord/Troll_cast_02.mp3"
    ],
    "mp3Text": "I will see your insides."
  },
  {
    "type": "voice",
    "mp3Url": [
      "https://coding.net/u/dovahkiin/p/tempData/git/raw/master/allmp3/Troll%20Warlord/Troll_cast_03.mp3"
    ],
    "mp3Text": "I'm coming for you."
  },
  {
    "headTitle": "Abilities",
    "type": "title"
  },
  {
    "imgUrl": "https://dota-mini-1256174840.cos.ap-shanghai.myqcloud.com/16px-Berserker%2527s_Rage_icon.png",
    "skillName": "Berserker's Rage",
    "type": "skill"
  },
  {
    "text": "Upon toggling on",
    "type": "middle"
  },
  {
    "type": "voice",
    "mp3Url": [
      "https://coding.net/u/dovahkiin/p/tempData/git/raw/master/allmp3/Troll%20Warlord/Troll_battletrance_06.mp3"
    ],
    "mp3Text": "Have at them."
  },
  {
    "type": "voice",
    "mp3Url": [
      "https://coding.net/u/dovahkiin/p/tempData/git/raw/master/allmp3/Troll%20Warlord/Troll_beserker_03.mp3"
    ],
    "mp3Text": "Feed my blades."
  },
  {
    "imgUrl": "https://dota-mini-1256174840.cos.ap-shanghai.myqcloud.com/16px-Whirling_Axes_%2528Ranged%2529_icon.png",
    "skillName": "Whirling Axes (Ranged)",
    "type": "skill"
  },
  {
    "text": "On cast",
    "type": "middle"
  },
  {
    "type": "voice",
    "mp3Url": [
      "https://coding.net/u/dovahkiin/p/tempData/git/raw/master/allmp3/Troll%20Warlord/Troll_whirlingaxes_02.mp3"
    ],
    "mp3Text": "Axes fly."
  },
  {
    "type": "voice",
    "mp3Url": [
      "https://coding.net/u/dovahkiin/p/tempData/git/raw/master/allmp3/Troll%20Warlord/Troll_whirlingaxes_03.mp3"
    ],
    "mp3Text": "Blades fly!"
  },
  {
    "type": "voice",
    "mp3Url": [
      "https://coding.net/u/dovahkiin/p/tempData/git/raw/master/allmp3/Troll%20Warlord/Troll_whirlingaxes_05.mp3"
    ],
    "mp3Text": "Axes of evil."
  },
  {
    "imgUrl": "https://dota-mini-1256174840.cos.ap-shanghai.myqcloud.com/16px-Whirling_Axes_%2528Melee%2529_icon.png",
    "skillName": "Whirling Axes (Melee)",
    "type": "skill"
  },
  {
    "text": "On cast",
    "type": "middle"
  },
  {
    "type": "voice",
    "mp3Url": [
      "https://coding.net/u/dovahkiin/p/tempData/git/raw/master/allmp3/Troll%20Warlord/Troll_whirlingaxes_01.mp3"
    ],
    "mp3Text": "Whirling."
  },
  {
    "type": "voice",
    "mp3Url": [
      "https://coding.net/u/dovahkiin/p/tempData/git/raw/master/allmp3/Troll%20Warlord/Troll_whirlingaxes_04.mp3"
    ],
    "mp3Text": "Give em a whirl."
  },
  {
    "type": "voice",
    "mp3Url": [
      "https://coding.net/u/dovahkiin/p/tempData/git/raw/master/allmp3/Troll%20Warlord/Troll_whirlingaxes_05.mp3"
    ],
    "mp3Text": "Axes of evil."
  },
  {
    "imgUrl": "http://dota.cn-sh2.ufileos.com/16px-Fervor_icon.png",
    "skillName": "Fervor",
    "type": "skill"
  },
  {
    "text": "Upon leveling",
    "type": "middle"
  },
  {
    "type": "voice",
    "mp3Url": [
      "https://coding.net/u/dovahkiin/p/tempData/git/raw/master/allmp3/Troll%20Warlord/Troll_fervor_01.mp3"
    ],
    "mp3Text": "I'm fervent all right!"
  },
  {
    "type": "voice",
    "mp3Url": [
      "https://coding.net/u/dovahkiin/p/tempData/git/raw/master/allmp3/Troll%20Warlord/Troll_fervor_03.mp3"
    ],
    "mp3Text": "Fervor rising."
  },
  {
    "type": "voice",
    "mp3Url": [
      "https://coding.net/u/dovahkiin/p/tempData/git/raw/master/allmp3/Troll%20Warlord/Troll_fervor_05.mp3"
    ],
    "mp3Text": "Come at me."
  },
  {
    "voices": []
  },
  {
    "text": "Upon leveling",
    "type": "middle"
  },
  {
    "type": "voice",
    "mp3Url": [
      "https://coding.net/u/dovahkiin/p/tempData/git/raw/master/allmp3/Troll%20Warlord/Troll_battletrance_04.mp3"
    ],
    "mp3Text": "I bring out the troll in everyone."
  },
  {
    "headTitle": "Leveling up",
    "type": "title"
  },
  {
    "type": "voice",
    "mp3Url": [
      "https://coding.net/u/dovahkiin/p/tempData/git/raw/master/allmp3/Troll%20Warlord/Troll_fervor_02.mp3"
    ],
    "mp3Text": "Pain is gain."
  },
  {
    "type": "voice",
    "mp3Url": [
      "https://coding.net/u/dovahkiin/p/tempData/git/raw/master/allmp3/Troll%20Warlord/Troll_fervor_04.mp3"
    ],
    "mp3Text": "That's it."
  },
  {
    "type": "voice",
    "mp3Url": [
      "https://coding.net/u/dovahkiin/p/tempData/git/raw/master/allmp3/Troll%20Warlord/Troll_fervor_06.mp3"
    ],
    "mp3Text": "More like it."
  },
  {
    "type": "voice",
    "mp3Url": [
      "https://coding.net/u/dovahkiin/p/tempData/git/raw/master/allmp3/Troll%20Warlord/Troll_levelup_01.mp3"
    ],
    "mp3Text": "They'll do what I tell them or regret it."
  },
  {
    "type": "voice",
    "mp3Url": [
      "https://coding.net/u/dovahkiin/p/tempData/git/raw/master/allmp3/Troll%20Warlord/Troll_levelup_02.mp3"
    ],
    "mp3Text": "A nasty business just got nastier."
  },
  {
    "type": "voice",
    "mp3Url": [
      "https://coding.net/u/dovahkiin/p/tempData/git/raw/master/allmp3/Troll%20Warlord/Troll_levelup_03.mp3"
    ],
    "mp3Text": "Yes, yes, hahahahah."
  },
  {
    "type": "voice",
    "mp3Url": [
      "https://coding.net/u/dovahkiin/p/tempData/git/raw/master/allmp3/Troll%20Warlord/Troll_levelup_04.mp3"
    ],
    "mp3Text": "Steeped in hatred!"
  },
  {
    "type": "voice",
    "mp3Url": [
      "https://coding.net/u/dovahkiin/p/tempData/git/raw/master/allmp3/Troll%20Warlord/Troll_levelup_05.mp3"
    ],
    "mp3Text": "You thought I was bad before?"
  },
  {
    "type": "voice",
    "mp3Url": [
      "https://coding.net/u/dovahkiin/p/tempData/git/raw/master/allmp3/Troll%20Warlord/Troll_levelup_06.mp3"
    ],
    "mp3Text": "The ultimate in trolling!"
  },
  {
    "type": "voice",
    "mp3Url": [
      "https://coding.net/u/dovahkiin/p/tempData/git/raw/master/allmp3/Troll%20Warlord/Troll_levelup_07.mp3"
    ],
    "mp3Text": "No last wishes, no second thoughts."
  },
  {
    "type": "voice",
    "mp3Url": [
      "https://coding.net/u/dovahkiin/p/tempData/git/raw/master/allmp3/Troll%20Warlord/Troll_levelup_08.mp3"
    ],
    "mp3Text": "Remorse? What was that again?"
  },
  {
    "type": "voice",
    "mp3Url": [
      "https://coding.net/u/dovahkiin/p/tempData/git/raw/master/allmp3/Troll%20Warlord/Troll_levelup_09.mp3"
    ],
    "mp3Text": "Hehehahah."
  },
  {
    "headTitle": "Killing an enemy",
    "type": "title"
  },
  {
    "type": "voice",
    "mp3Url": [
      "https://coding.net/u/dovahkiin/p/tempData/git/raw/master/allmp3/Troll%20Warlord/Troll_kill_01.mp3"
    ],
    "mp3Text": "Death is my way of life."
  },
  {
    "type": "voice",
    "mp3Url": [
      "https://coding.net/u/dovahkiin/p/tempData/git/raw/master/allmp3/Troll%20Warlord/Troll_kill_02.mp3"
    ],
    "mp3Text": "Killing you was the least I could do."
  },
  {
    "type": "voice",
    "mp3Url": [
      "https://coding.net/u/dovahkiin/p/tempData/git/raw/master/allmp3/Troll%20Warlord/Troll_kill_03.mp3"
    ],
    "mp3Text": "Come back and die again."
  },
  {
    "type": "voice",
    "mp3Url": [
      "https://coding.net/u/dovahkiin/p/tempData/git/raw/master/allmp3/Troll%20Warlord/Troll_kill_04.mp3"
    ],
    "mp3Text": "I'll be here when you get back."
  },
  {
    "type": "voice",
    "mp3Url": [
      "https://coding.net/u/dovahkiin/p/tempData/git/raw/master/allmp3/Troll%20Warlord/Troll_kill_05.mp3"
    ],
    "mp3Text": "Death brings an end to pain, unfortunately."
  },
  {
    "type": "voice",
    "mp3Url": [
      "https://coding.net/u/dovahkiin/p/tempData/git/raw/master/allmp3/Troll%20Warlord/Troll_kill_06.mp3"
    ],
    "mp3Text": "You were a casualty of war."
  },
  {
    "type": "voice",
    "mp3Url": [
      "https://coding.net/u/dovahkiin/p/tempData/git/raw/master/allmp3/Troll%20Warlord/Troll_kill_07.mp3"
    ],
    "mp3Text": "What's war-torn can't be mended."
  },
  {
    "type": "voice",
    "mp3Url": [
      "https://coding.net/u/dovahkiin/p/tempData/git/raw/master/allmp3/Troll%20Warlord/Troll_kill_08.mp3"
    ],
    "mp3Text": "Pay attention when I kill you."
  },
  {
    "type": "voice",
    "mp3Url": [
      "https://coding.net/u/dovahkiin/p/tempData/git/raw/master/allmp3/Troll%20Warlord/Troll_kill_09.mp3"
    ],
    "mp3Text": "Why do I enjoy this so much."
  },
  {
    "type": "voice",
    "mp3Url": [
      "https://coding.net/u/dovahkiin/p/tempData/git/raw/master/allmp3/Troll%20Warlord/Troll_kill_10.mp3"
    ],
    "mp3Text": "I'll pry your eyes from your skull."
  },
  {
    "type": "voice",
    "mp3Url": [
      "https://coding.net/u/dovahkiin/p/tempData/git/raw/master/allmp3/Troll%20Warlord/Troll_kill_11.mp3"
    ],
    "mp3Text": "You been trolled."
  },
  {
    "type": "voice",
    "mp3Url": [
      "https://coding.net/u/dovahkiin/p/tempData/git/raw/master/allmp3/Troll%20Warlord/Troll_kill_12.mp3"
    ],
    "mp3Text": "Fortune favors the trolled."
  },
  {
    "type": "voice",
    "mp3Url": [
      "https://coding.net/u/dovahkiin/p/tempData/git/raw/master/allmp3/Troll%20Warlord/Troll_kill_13.mp3"
    ],
    "mp3Text": "Ehaheh heh hah hah heha."
  },
  {
    "type": "voice",
    "mp3Url": [
      "https://coding.net/u/dovahkiin/p/tempData/git/raw/master/allmp3/Troll%20Warlord/Troll_kill_14.mp3"
    ],
    "mp3Text": "Heh he heh hah heh."
  },
  {
    "type": "voice",
    "mp3Url": [
      "https://coding.net/u/dovahkiin/p/tempData/git/raw/master/allmp3/Troll%20Warlord/Troll_kill_15.mp3"
    ],
    "mp3Text": "Hah hah hah heh heh hah heh."
  },
  {
    "type": "voice",
    "mp3Url": [
      "https://coding.net/u/dovahkiin/p/tempData/git/raw/master/allmp3/Troll%20Warlord/Troll_laugh_01.mp3"
    ],
    "mp3Text": "Yeahhh."
  },
  {
    "type": "voice",
    "mp3Url": [
      "https://coding.net/u/dovahkiin/p/tempData/git/raw/master/allmp3/Troll%20Warlord/Troll_laugh_02.mp3"
    ],
    "mp3Text": "Yeheheheheh."
  },
  {
    "type": "voice",
    "mp3Url": [
      "https://coding.net/u/dovahkiin/p/tempData/git/raw/master/allmp3/Troll%20Warlord/Troll_laugh_03.mp3"
    ],
    "mp3Text": "He heh hah heh heheheh."
  },
  {
    "type": "voice",
    "mp3Url": [
      "https://coding.net/u/dovahkiin/p/tempData/git/raw/master/allmp3/Troll%20Warlord/Troll_laugh_04.mp3"
    ],
    "mp3Text": "Hahahahahah."
  },
  {
    "type": "voice",
    "mp3Url": [
      "https://coding.net/u/dovahkiin/p/tempData/git/raw/master/allmp3/Troll%20Warlord/Troll_laugh_05.mp3"
    ],
    "mp3Text": "Yaaahahahaahhah."
  },
  {
    "type": "voice",
    "mp3Url": [
      "https://coding.net/u/dovahkiin/p/tempData/git/raw/master/allmp3/Troll%20Warlord/Troll_laugh_07.mp3"
    ],
    "mp3Text": "Heheheh."
  },
  {
    "type": "voice",
    "mp3Url": [
      "https://coding.net/u/dovahkiin/p/tempData/git/raw/master/allmp3/Troll%20Warlord/Troll_rival_27.mp3"
    ],
    "mp3Text": "Enjoy your ban."
  },
  {
    "text": "Killing a specific enemy",
    "type": "subTitle"
  },
  {
    "type": "voice",
    "mp3Url": [
      "https://coding.net/u/dovahkiin/p/tempData/git/raw/master/allmp3/Troll%20Warlord/Troll_rival_01.mp3"
    ],
    "mp3Text": "Even stone can't turn my blades.",
    "imgs": [
      {
        "img": "http://dota.cn-sh2.ufileos.com/16px-Tiny_minimap_icon.png",
        "name": "Tiny"
      }
    ]
  },
  {
    "type": "voice",
    "mp3Url": [
      "https://coding.net/u/dovahkiin/p/tempData/git/raw/master/allmp3/Troll%20Warlord/Troll_rival_02.mp3"
    ],
    "mp3Text": "Your life is trunk-cated, heh hah he hah.",
    "imgs": [
      {
        "img": "http://dota.cn-sh2.ufileos.com/16px-Treant_Protector_minimap_icon.png",
        "name": "Treant Protector"
      }
    ]
  },
  {
    "type": "voice",
    "mp3Url": [
      "https://coding.net/u/dovahkiin/p/tempData/git/raw/master/allmp3/Troll%20Warlord/Troll_rival_03.mp3"
    ],
    "mp3Text": "Your flesh corrupted.",
    "imgs": [
      {
        "img": "http://dota.cn-sh2.ufileos.com/16px-Necrophos_minimap_icon.png",
        "name": "Necrophos"
      }
    ]
  },
  {
    "type": "voice",
    "mp3Url": [
      "https://coding.net/u/dovahkiin/p/tempData/git/raw/master/allmp3/Troll%20Warlord/Troll_rival_04.mp3"
    ],
    "mp3Text": "There's no thread of yours I can't snarl up.",
    "imgs": [
      {
        "img": "http://dota.cn-sh2.ufileos.com/16px-Weaver_minimap_icon.png",
        "name": "Weaver"
      }
    ]
  },
  {
    "type": "voice",
    "mp3Url": [
      "https://coding.net/u/dovahkiin/p/tempData/git/raw/master/allmp3/Troll%20Warlord/Troll_rival_05.mp3"
    ],
    "mp3Text": "Whatever form you take, I'll dominate it.",
    "imgs": [
      {
        "img": "http://dota.cn-sh2.ufileos.com/16px-Morphling_minimap_icon.png",
        "name": "Morphling"
      }
    ]
  },
  {
    "type": "voice",
    "mp3Url": [
      "https://coding.net/u/dovahkiin/p/tempData/git/raw/master/allmp3/Troll%20Warlord/Troll_rival_06.mp3"
    ],
    "mp3Text": "I'll kill you again, and again, and again.",
    "imgs": [
      {
        "img": "http://dota.cn-sh2.ufileos.com/16px-Huskar_minimap_icon.png",
        "name": "Huskar"
      }
    ]
  },
  {
    "type": "voice",
    "mp3Url": [
      "https://coding.net/u/dovahkiin/p/tempData/git/raw/master/allmp3/Troll%20Warlord/Troll_rival_24.mp3"
    ],
    "mp3Text": "You remind me of me. I hate you most of all!",
    "imgs": [
      {
        "img": "http://dota.cn-sh2.ufileos.com/16px-Huskar_minimap_icon.png",
        "name": "Huskar"
      }
    ]
  },
  {
    "type": "voice",
    "mp3Url": [
      "https://coding.net/u/dovahkiin/p/tempData/git/raw/master/allmp3/Troll%20Warlord/Troll_rival_07.mp3"
    ],
    "mp3Text": "Not so dazzling in death.",
    "imgs": [
      {
        "img": "http://dota.cn-sh2.ufileos.com/16px-Dazzle_minimap_icon.png",
        "name": "Dazzle"
      }
    ]
  },
  {
    "type": "voice",
    "mp3Url": [
      "https://coding.net/u/dovahkiin/p/tempData/git/raw/master/allmp3/Troll%20Warlord/Troll_rival_08.mp3"
    ],
    "mp3Text": "No suffering is enough for you.",
    "imgs": [
      {
        "img": "http://dota.cn-sh2.ufileos.com/16px-Dazzle_minimap_icon.png",
        "name": "Dazzle"
      }
    ]
  },
  {
    "type": "voice",
    "mp3Url": [
      "https://coding.net/u/dovahkiin/p/tempData/git/raw/master/allmp3/Troll%20Warlord/Troll_rival_09.mp3"
    ],
    "mp3Text": "Bow before your warlord.",
    "imgs": [
      {
        "img": "http://dota.cn-sh2.ufileos.com/16px-Shadow_Shaman_minimap_icon.png",
        "name": "Shadow Shaman"
      }
    ]
  },
  {
    "type": "voice",
    "mp3Url": [
      "https://coding.net/u/dovahkiin/p/tempData/git/raw/master/allmp3/Troll%20Warlord/Troll_rival_10.mp3"
    ],
    "mp3Text": "The trolls from the hills are barely trolls at all.",
    "imgs": [
      {
        "img": "http://dota.cn-sh2.ufileos.com/16px-Shadow_Shaman_minimap_icon.png",
        "name": "Shadow Shaman"
      }
    ]
  },
  {
    "type": "voice",
    "mp3Url": [
      "https://coding.net/u/dovahkiin/p/tempData/git/raw/master/allmp3/Troll%20Warlord/Troll_rival_11.mp3"
    ],
    "mp3Text": "Hill trolls are the weakest of our kind.",
    "imgs": [
      {
        "img": "http://dota.cn-sh2.ufileos.com/16px-Shadow_Shaman_minimap_icon.png",
        "name": "Shadow Shaman"
      }
    ]
  },
  {
    "type": "voice",
    "mp3Url": [
      "https://coding.net/u/dovahkiin/p/tempData/git/raw/master/allmp3/Troll%20Warlord/Troll_rival_12.mp3"
    ],
    "mp3Text": "I hear your keening cry.",
    "imgs": [
      {
        "img": "http://dota.cn-sh2.ufileos.com/16px-Tinker_minimap_icon.png",
        "name": "Tinker"
      }
    ]
  },
  {
    "type": "voice",
    "mp3Url": [
      "https://coding.net/u/dovahkiin/p/tempData/git/raw/master/allmp3/Troll%20Warlord/Troll_rival_13.mp3"
    ],
    "mp3Text": "Your mind was not so keen as my blades.",
    "imgs": [
      {
        "img": "http://dota.cn-sh2.ufileos.com/16px-Tinker_minimap_icon.png",
        "name": "Tinker"
      }
    ]
  },
  {
    "type": "voice",
    "mp3Url": [
      "https://coding.net/u/dovahkiin/p/tempData/git/raw/master/allmp3/Troll%20Warlord/Troll_rival_14.mp3"
    ],
    "mp3Text": "Ride your ogre to hell, small-keen.",
    "imgs": [
      {
        "img": "http://dota.cn-sh2.ufileos.com/16px-Alchemist_minimap_icon.png",
        "name": "Alchemist"
      }
    ]
  },
  {
    "type": "voice",
    "mp3Url": [
      "https://coding.net/u/dovahkiin/p/tempData/git/raw/master/allmp3/Troll%20Warlord/Troll_rival_15.mp3"
    ],
    "mp3Text": "Ogre, you had a growth on your neck. I cut it off.",
    "imgs": [
      {
        "img": "http://dota.cn-sh2.ufileos.com/16px-Alchemist_minimap_icon.png",
        "name": "Alchemist"
      }
    ]
  },
  {
    "type": "voice",
    "mp3Url": [
      "https://coding.net/u/dovahkiin/p/tempData/git/raw/master/allmp3/Troll%20Warlord/Troll_rival_16.mp3"
    ],
    "mp3Text": "I knocked that chip off your shoulder.",
    "imgs": [
      {
        "img": "http://dota.cn-sh2.ufileos.com/16px-Alchemist_minimap_icon.png",
        "name": "Alchemist"
      }
    ]
  },
  {
    "type": "voice",
    "mp3Url": [
      "https://coding.net/u/dovahkiin/p/tempData/git/raw/master/allmp3/Troll%20Warlord/Troll_rival_17.mp3"
    ],
    "mp3Text": "I suffer you special, Sniper.",
    "imgs": [
      {
        "img": "http://dota.cn-sh2.ufileos.com/16px-Sniper_minimap_icon.png",
        "name": "Sniper"
      }
    ]
  },
  {
    "type": "voice",
    "mp3Url": [
      "https://coding.net/u/dovahkiin/p/tempData/git/raw/master/allmp3/Troll%20Warlord/Troll_rival_18.mp3"
    ],
    "mp3Text": "You keen folk cower behind your gadgets.",
    "imgs": [
      {
        "img": "http://dota.cn-sh2.ufileos.com/16px-Gyrocopter_minimap_icon.png",
        "name": "Gyrocopter"
      }
    ]
  },
  {
    "type": "voice",
    "mp3Url": [
      "https://coding.net/u/dovahkiin/p/tempData/git/raw/master/allmp3/Troll%20Warlord/Troll_rival_19.mp3"
    ],
    "mp3Text": "Your contraption becomes your coffin.",
    "imgs": [
      {
        "img": "http://dota.cn-sh2.ufileos.com/16px-Gyrocopter_minimap_icon.png",
        "name": "Gyrocopter"
      }
    ]
  },
  {
    "type": "voice",
    "mp3Url": [
      "https://coding.net/u/dovahkiin/p/tempData/git/raw/master/allmp3/Troll%20Warlord/Troll_rival_20.mp3"
    ],
    "mp3Text": "Your clock stops.",
    "imgs": [
      {
        "img": "http://dota.cn-sh2.ufileos.com/16px-Clockwerk_minimap_icon.png",
        "name": "Clockwerk"
      }
    ]
  },
  {
    "type": "voice",
    "mp3Url": [
      "https://coding.net/u/dovahkiin/p/tempData/git/raw/master/allmp3/Troll%20Warlord/Troll_rival_21.mp3"
    ],
    "mp3Text": "You were strong for a keen, but that's not saying much.",
    "imgs": [
      {
        "img": "http://dota.cn-sh2.ufileos.com/16px-Clockwerk_minimap_icon.png",
        "name": "Clockwerk"
      }
    ]
  },
  {
    "type": "voice",
    "mp3Url": [
      "https://coding.net/u/dovahkiin/p/tempData/git/raw/master/allmp3/Troll%20Warlord/Troll_rival_22.mp3"
    ],
    "mp3Text": "Not so cheerful now, are you?",
    "imgs": [
      {
        "img": "http://dota.cn-sh2.ufileos.com/16px-Enchantress_minimap_icon.png",
        "name": "Enchantress"
      }
    ]
  },
  {
    "type": "voice",
    "mp3Url": [
      "https://coding.net/u/dovahkiin/p/tempData/git/raw/master/allmp3/Troll%20Warlord/Troll_rival_23.mp3"
    ],
    "mp3Text": "Do you know what I hate? You!",
    "imgs": [
      {
        "img": "http://dota.cn-sh2.ufileos.com/16px-Enchantress_minimap_icon.png",
        "name": "Enchantress"
      }
    ]
  },
  {
    "type": "voice",
    "mp3Url": [
      "https://coding.net/u/dovahkiin/p/tempData/git/raw/master/allmp3/Troll%20Warlord/Troll_rival_25.mp3"
    ],
    "mp3Text": "An axe for an axe.",
    "imgs": [
      {
        "img": "http://dota.cn-sh2.ufileos.com/16px-Axe_minimap_icon.png",
        "name": "Axe"
      }
    ]
  },
  {
    "type": "voice",
    "mp3Url": [
      "https://coding.net/u/dovahkiin/p/tempData/git/raw/master/allmp3/Troll%20Warlord/Troll_rival_26.mp3"
    ],
    "mp3Text": "It's not the size of the axe that matters, it's how you swing it.",
    "imgs": [
      {
        "img": "http://dota.cn-sh2.ufileos.com/16px-Axe_minimap_icon.png",
        "name": "Axe"
      }
    ]
  },
  {
    "text": "First Blood",
    "type": "subTitle"
  },
  {
    "type": "voice",
    "mp3Url": [
      "https://coding.net/u/dovahkiin/p/tempData/git/raw/master/allmp3/Troll%20Warlord/Troll_firstblood_01.mp3"
    ],
    "mp3Text": "First blood, last word."
  },
  {
    "type": "voice",
    "mp3Url": [
      "https://coding.net/u/dovahkiin/p/tempData/git/raw/master/allmp3/Troll%20Warlord/Troll_firstblood_02.mp3"
    ],
    "mp3Text": "On to my next victim."
  },
  {
    "type": "voice",
    "mp3Url": [
      "https://coding.net/u/dovahkiin/p/tempData/git/raw/master/allmp3/Troll%20Warlord/Troll_firstblood_03.mp3"
    ],
    "mp3Text": "Nyaheh heh, first blood, last word, I got it all."
  },
  {
    "headTitle": "Meeting an ally",
    "type": "title"
  },
  {
    "text": "During earlygame, within 1000 radius",
    "type": "small"
  },
  {
    "type": "voice",
    "mp3Url": [
      "https://coding.net/u/dovahkiin/p/tempData/git/raw/master/allmp3/Troll%20Warlord/Troll_ally_03.mp3"
    ],
    "mp3Text": "Let's kill these fools before we start in on each other."
  },
  {
    "type": "voice",
    "mp3Url": [
      "https://coding.net/u/dovahkiin/p/tempData/git/raw/master/allmp3/Troll%20Warlord/Troll_ally_01.mp3"
    ],
    "mp3Text": "I need no allies."
  },
  {
    "type": "voice",
    "mp3Url": [
      "https://coding.net/u/dovahkiin/p/tempData/git/raw/master/allmp3/Troll%20Warlord/Troll_ally_10.mp3"
    ],
    "mp3Text": "I can see I'll have to carry us to victory."
  },
  {
    "type": "voice",
    "mp3Url": [
      "https://coding.net/u/dovahkiin/p/tempData/git/raw/master/allmp3/Troll%20Warlord/Troll_ally_02.mp3"
    ],
    "mp3Text": "I kill my enemies first, my allies next."
  },
  {
    "type": "voice",
    "mp3Url": [
      "https://coding.net/u/dovahkiin/p/tempData/git/raw/master/allmp3/Troll%20Warlord/Troll_ally_05.mp3"
    ],
    "mp3Text": "Would that I could fight alone."
  },
  {
    "type": "voice",
    "mp3Url": [
      "https://coding.net/u/dovahkiin/p/tempData/git/raw/master/allmp3/Troll%20Warlord/Troll_ally_09.mp3"
    ],
    "mp3Text": "Why are my allies so weak and pathetic?"
  },
  {
    "type": "voice",
    "mp3Url": [
      "https://coding.net/u/dovahkiin/p/tempData/git/raw/master/allmp3/Troll%20Warlord/Troll_ally_12.mp3"
    ],
    "mp3Text": "Just try not to feed."
  },
  {
    "type": "voice",
    "mp3Url": [
      "https://coding.net/u/dovahkiin/p/tempData/git/raw/master/allmp3/Troll%20Warlord/Troll_ally_04.mp3"
    ],
    "mp3Text": "I'll get to you later."
  },
  {
    "type": "voice",
    "mp3Url": [
      "https://coding.net/u/dovahkiin/p/tempData/git/raw/master/allmp3/Troll%20Warlord/Troll_ally_06.mp3"
    ],
    "mp3Text": "I'd be better off fighting alone."
  },
  {
    "type": "voice",
    "mp3Url": [
      "https://coding.net/u/dovahkiin/p/tempData/git/raw/master/allmp3/Troll%20Warlord/Troll_ally_07.mp3"
    ],
    "mp3Text": "Don't get in my way."
  },
  {
    "type": "voice",
    "mp3Url": [
      "https://coding.net/u/dovahkiin/p/tempData/git/raw/master/allmp3/Troll%20Warlord/Troll_ally_08.mp3"
    ],
    "mp3Text": "You've got to be kidding."
  },
  {
    "type": "voice",
    "mp3Url": [
      "https://coding.net/u/dovahkiin/p/tempData/git/raw/master/allmp3/Troll%20Warlord/Troll_ally_11.mp3"
    ],
    "mp3Text": "Try not to feed."
  },
  {
    "headTitle": "Last hitting",
    "type": "title"
  },
  {
    "type": "voice",
    "mp3Url": [
      "https://coding.net/u/dovahkiin/p/tempData/git/raw/master/allmp3/Troll%20Warlord/Troll_lasthit_01.mp3"
    ],
    "mp3Text": "Gold for my armor."
  },
  {
    "type": "voice",
    "mp3Url": [
      "https://coding.net/u/dovahkiin/p/tempData/git/raw/master/allmp3/Troll%20Warlord/Troll_lasthit_02.mp3"
    ],
    "mp3Text": "My war chest grows."
  },
  {
    "type": "voice",
    "mp3Url": [
      "https://coding.net/u/dovahkiin/p/tempData/git/raw/master/allmp3/Troll%20Warlord/Troll_lasthit_03.mp3"
    ],
    "mp3Text": "All's fair in war."
  },
  {
    "type": "voice",
    "mp3Url": [
      "https://coding.net/u/dovahkiin/p/tempData/git/raw/master/allmp3/Troll%20Warlord/Troll_lasthit_04.mp3"
    ],
    "mp3Text": "Pay the troll."
  },
  {
    "type": "voice",
    "mp3Url": [
      "https://coding.net/u/dovahkiin/p/tempData/git/raw/master/allmp3/Troll%20Warlord/Troll_lasthit_05.mp3"
    ],
    "mp3Text": "Gold for steel."
  },
  {
    "type": "voice",
    "mp3Url": [
      "https://coding.net/u/dovahkiin/p/tempData/git/raw/master/allmp3/Troll%20Warlord/Troll_lasthit_06.mp3"
    ],
    "mp3Text": "Death is too good."
  },
  {
    "type": "voice",
    "mp3Url": [
      "https://coding.net/u/dovahkiin/p/tempData/git/raw/master/allmp3/Troll%20Warlord/Troll_lasthit_07.mp3"
    ],
    "mp3Text": "Down you go."
  },
  {
    "type": "voice",
    "mp3Url": [
      "https://coding.net/u/dovahkiin/p/tempData/git/raw/master/allmp3/Troll%20Warlord/Troll_lasthit_08.mp3"
    ],
    "mp3Text": "You've been trolled."
  },
  {
    "type": "voice",
    "mp3Url": [
      "https://coding.net/u/dovahkiin/p/tempData/git/raw/master/allmp3/Troll%20Warlord/Troll_lasthit_09.mp3"
    ],
    "mp3Text": "Go on, feed me."
  },
  {
    "headTitle": "Denying",
    "type": "title"
  },
  {
    "type": "voice",
    "mp3Url": [
      "https://coding.net/u/dovahkiin/p/tempData/git/raw/master/allmp3/Troll%20Warlord/Troll_deny_01.mp3"
    ],
    "mp3Text": "Denied."
  },
  {
    "type": "voice",
    "mp3Url": [
      "https://coding.net/u/dovahkiin/p/tempData/git/raw/master/allmp3/Troll%20Warlord/Troll_deny_02.mp3"
    ],
    "mp3Text": "Denied."
  },
  {
    "type": "voice",
    "mp3Url": [
      "https://coding.net/u/dovahkiin/p/tempData/git/raw/master/allmp3/Troll%20Warlord/Troll_deny_03.mp3"
    ],
    "mp3Text": "Denied."
  },
  {
    "type": "voice",
    "mp3Url": [
      "https://coding.net/u/dovahkiin/p/tempData/git/raw/master/allmp3/Troll%20Warlord/Troll_deny_04.mp3"
    ],
    "mp3Text": "Uh-uh."
  },
  {
    "type": "voice",
    "mp3Url": [
      "https://coding.net/u/dovahkiin/p/tempData/git/raw/master/allmp3/Troll%20Warlord/Troll_deny_05.mp3"
    ],
    "mp3Text": "No, no."
  },
  {
    "type": "voice",
    "mp3Url": [
      "https://coding.net/u/dovahkiin/p/tempData/git/raw/master/allmp3/Troll%20Warlord/Troll_deny_06.mp3"
    ],
    "mp3Text": "Not."
  },
  {
    "type": "voice",
    "mp3Url": [
      "https://coding.net/u/dovahkiin/p/tempData/git/raw/master/allmp3/Troll%20Warlord/Troll_deny_07.mp3"
    ],
    "mp3Text": "I don't think so."
  },
  {
    "type": "voice",
    "mp3Url": [
      "https://coding.net/u/dovahkiin/p/tempData/git/raw/master/allmp3/Troll%20Warlord/Troll_deny_08.mp3"
    ],
    "mp3Text": "Too bad."
  },
  {
    "type": "voice",
    "mp3Url": [
      "https://coding.net/u/dovahkiin/p/tempData/git/raw/master/allmp3/Troll%20Warlord/Troll_deny_09.mp3"
    ],
    "mp3Text": "Unfortunate."
  },
  {
    "type": "voice",
    "mp3Url": [
      "https://coding.net/u/dovahkiin/p/tempData/git/raw/master/allmp3/Troll%20Warlord/Troll_deny_10.mp3"
    ],
    "mp3Text": "That felt good."
  },
  {
    "type": "voice",
    "mp3Url": [
      "https://coding.net/u/dovahkiin/p/tempData/git/raw/master/allmp3/Troll%20Warlord/Troll_deny_11.mp3"
    ],
    "mp3Text": "Hehehah heh hah."
  },
  {
    "type": "voice",
    "mp3Url": [
      "https://coding.net/u/dovahkiin/p/tempData/git/raw/master/allmp3/Troll%20Warlord/Troll_deny_12.mp3"
    ],
    "mp3Text": "Hah heh hah hah hah."
  },
  {
    "type": "voice",
    "mp3Url": [
      "https://coding.net/u/dovahkiin/p/tempData/git/raw/master/allmp3/Troll%20Warlord/Troll_deny_13.mp3"
    ],
    "mp3Text": "Denied."
  },
  {
    "type": "voice",
    "mp3Url": [
      "https://coding.net/u/dovahkiin/p/tempData/git/raw/master/allmp3/Troll%20Warlord/Troll_deny_14.mp3"
    ],
    "mp3Text": "Denied."
  },
  {
    "type": "voice",
    "mp3Url": [
      "https://coding.net/u/dovahkiin/p/tempData/git/raw/master/allmp3/Troll%20Warlord/Troll_deny_15.mp3"
    ],
    "mp3Text": "Denied."
  },
  {
    "type": "voice",
    "mp3Url": [
      "https://coding.net/u/dovahkiin/p/tempData/git/raw/master/allmp3/Troll%20Warlord/Troll_deny_16.mp3"
    ],
    "mp3Text": "Denied."
  },
  {
    "type": "voice",
    "mp3Url": [
      "https://coding.net/u/dovahkiin/p/tempData/git/raw/master/allmp3/Troll%20Warlord/Troll_deny_17.mp3"
    ],
    "mp3Text": "Denied."
  },
  {
    "headTitle": "Acquiring an item",
    "type": "title"
  },
  {
    "type": "voice",
    "mp3Url": [
      "https://coding.net/u/dovahkiin/p/tempData/git/raw/master/allmp3/Troll%20Warlord/Troll_purch_01.mp3"
    ],
    "mp3Text": "I'd rather strip this from a corpse."
  },
  {
    "type": "voice",
    "mp3Url": [
      "https://coding.net/u/dovahkiin/p/tempData/git/raw/master/allmp3/Troll%20Warlord/Troll_purch_02.mp3"
    ],
    "mp3Text": "I'll kill you later, Keeper."
  },
  {
    "type": "voice",
    "mp3Url": [
      "https://coding.net/u/dovahkiin/p/tempData/git/raw/master/allmp3/Troll%20Warlord/Troll_purch_03.mp3"
    ],
    "mp3Text": "Keep on smiling, Keeper, it won't last."
  },
  {
    "type": "voice",
    "mp3Url": [
      "https://coding.net/u/dovahkiin/p/tempData/git/raw/master/allmp3/Troll%20Warlord/Troll_shop_11.mp3"
    ],
    "mp3Text": "Where's the complaint department?"
  },
  {
    "text": "Acquiring a specific item",
    "type": "subTitle"
  },
  {
    "type": "voice",
    "mp3Url": [
      "https://coding.net/u/dovahkiin/p/tempData/git/raw/master/allmp3/Troll%20Warlord/Troll_scepter_01.mp3"
    ],
    "mp3Text": "Ah, scepter.",
    "imgs": [
      {
        "img": "https://dota-mini-1256174840.cos.ap-shanghai.myqcloud.com/20px-Aghanim%2527s_Scepter_icon.png",
        "name": "Aghanim's Scepter (4200)"
      }
    ]
  },
  {
    "type": "voice",
    "mp3Url": [
      "https://coding.net/u/dovahkiin/p/tempData/git/raw/master/allmp3/Troll%20Warlord/Troll_scepter_02.mp3"
    ],
    "mp3Text": "I'll cave in their skulls with this.",
    "imgs": [
      {
        "img": "https://dota-mini-1256174840.cos.ap-shanghai.myqcloud.com/20px-Aghanim%2527s_Scepter_icon.png",
        "name": "Aghanim's Scepter (4200)"
      }
    ]
  },
  {
    "type": "voice",
    "mp3Url": [
      "https://coding.net/u/dovahkiin/p/tempData/git/raw/master/allmp3/Troll%20Warlord/Troll_blink_01.mp3"
    ],
    "mp3Text": "Blink dagger.",
    "imgs": [
      {
        "img": "http://dota.cn-sh2.ufileos.com/20px-Blink_Dagger_icon.png",
        "name": "Blink Dagger (2250)"
      }
    ]
  },
  {
    "type": "voice",
    "mp3Url": [
      "https://coding.net/u/dovahkiin/p/tempData/git/raw/master/allmp3/Troll%20Warlord/Troll_blink_02.mp3"
    ],
    "mp3Text": "The better to carve out their living hearts.",
    "imgs": [
      {
        "img": "http://dota.cn-sh2.ufileos.com/20px-Blink_Dagger_icon.png",
        "name": "Blink Dagger (2250)"
      }
    ]
  },
  {
    "type": "voice",
    "mp3Url": [
      "https://coding.net/u/dovahkiin/p/tempData/git/raw/master/allmp3/Troll%20Warlord/Troll_items_01.mp3"
    ],
    "mp3Text": "Black King Bar.",
    "imgs": [
      {
        "img": "http://dota.cn-sh2.ufileos.com/20px-Black_King_Bar_icon.png",
        "name": "Black King Bar (3975)"
      }
    ]
  },
  {
    "type": "voice",
    "mp3Url": [
      "https://coding.net/u/dovahkiin/p/tempData/git/raw/master/allmp3/Troll%20Warlord/Troll_items_02.mp3"
    ],
    "mp3Text": "Mask of madness? Seriously?",
    "imgs": [
      {
        "img": "http://dota.cn-sh2.ufileos.com/20px-Mask_of_Madness_icon.png",
        "name": "Mask of Madness (1975)"
      }
    ]
  },
  {
    "type": "voice",
    "mp3Url": [
      "https://coding.net/u/dovahkiin/p/tempData/git/raw/master/allmp3/Troll%20Warlord/Troll_items_03.mp3"
    ],
    "mp3Text": "Monkey King Troll.",
    "imgs": [
      {
        "img": "http://dota.cn-sh2.ufileos.com/20px-Monkey_King_Bar_icon.png",
        "name": "Monkey King Bar (4175)"
      }
    ]
  },
  {
    "type": "voice",
    "mp3Url": [
      "https://coding.net/u/dovahkiin/p/tempData/git/raw/master/allmp3/Troll%20Warlord/Troll_items_04.mp3"
    ],
    "mp3Text": "Satanic.",
    "imgs": [
      {
        "img": "http://dota.cn-sh2.ufileos.com/20px-Satanic_icon.png",
        "name": "Satanic (5500)"
      }
    ]
  },
  {
    "type": "voice",
    "mp3Url": [
      "https://coding.net/u/dovahkiin/p/tempData/git/raw/master/allmp3/Troll%20Warlord/Troll_items_05.mp3"
    ],
    "mp3Text": "Butterfly.",
    "imgs": [
      {
        "img": "http://dota.cn-sh2.ufileos.com/20px-Butterfly_icon.png",
        "name": "Butterfly (5475)"
      }
    ]
  },
  {
    "type": "voice",
    "mp3Url": [
      "https://coding.net/u/dovahkiin/p/tempData/git/raw/master/allmp3/Troll%20Warlord/Troll_items_06.mp3"
    ],
    "mp3Text": "Assault Cuirass.",
    "imgs": [
      {
        "img": "http://dota.cn-sh2.ufileos.com/20px-Assault_Cuirass_icon.png",
        "name": "Assault Cuirass (5250)"
      }
    ]
  },
  {
    "type": "voice",
    "mp3Url": [
      "https://coding.net/u/dovahkiin/p/tempData/git/raw/master/allmp3/Troll%20Warlord/Troll_immort_01.mp3"
    ],
    "mp3Text": "Immortality.",
    "imgs": [
      {
        "img": "http://dota.cn-sh2.ufileos.com/20px-Aegis_of_the_Immortal_icon.png",
        "name": "Aegis of the Immortal"
      }
    ]
  },
  {
    "type": "voice",
    "mp3Url": [
      "https://coding.net/u/dovahkiin/p/tempData/git/raw/master/allmp3/Troll%20Warlord/Troll_immort_02.mp3"
    ],
    "mp3Text": "The best trolls never die.",
    "imgs": [
      {
        "img": "http://dota.cn-sh2.ufileos.com/20px-Aegis_of_the_Immortal_icon.png",
        "name": "Aegis of the Immortal"
      }
    ]
  },
  {
    "headTitle": "Dying",
    "type": "title"
  },
  {
    "type": "voice",
    "mp3Url": [
      "https://coding.net/u/dovahkiin/p/tempData/git/raw/master/allmp3/Troll%20Warlord/Troll_death_01.mp3"
    ],
    "mp3Text": "No."
  },
  {
    "type": "voice",
    "mp3Url": [
      "https://coding.net/u/dovahkiin/p/tempData/git/raw/master/allmp3/Troll%20Warlord/Troll_death_02.mp3"
    ],
    "mp3Text": "No."
  },
  {
    "type": "voice",
    "mp3Url": [
      "https://coding.net/u/dovahkiin/p/tempData/git/raw/master/allmp3/Troll%20Warlord/Troll_death_03.mp3"
    ],
    "mp3Text": "You'll suffer in kind."
  },
  {
    "type": "voice",
    "mp3Url": [
      "https://coding.net/u/dovahkiin/p/tempData/git/raw/master/allmp3/Troll%20Warlord/Troll_death_04.mp3"
    ],
    "mp3Text": "Turn about, ain't fair."
  },
  {
    "type": "voice",
    "mp3Url": [
      "https://coding.net/u/dovahkiin/p/tempData/git/raw/master/allmp3/Troll%20Warlord/Troll_death_05.mp3"
    ],
    "mp3Text": "This can't be happening."
  },
  {
    "type": "voice",
    "mp3Url": [
      "https://coding.net/u/dovahkiin/p/tempData/git/raw/master/allmp3/Troll%20Warlord/Troll_death_06.mp3"
    ],
    "mp3Text": "My hate will bring me back."
  },
  {
    "type": "voice",
    "mp3Url": [
      "https://coding.net/u/dovahkiin/p/tempData/git/raw/master/allmp3/Troll%20Warlord/Troll_death_07.mp3"
    ],
    "mp3Text": "You got lucky that time."
  },
  {
    "type": "voice",
    "mp3Url": [
      "https://coding.net/u/dovahkiin/p/tempData/git/raw/master/allmp3/Troll%20Warlord/Troll_death_08.mp3"
    ],
    "mp3Text": "Hell has no room for my kind."
  },
  {
    "type": "voice",
    "mp3Url": [
      "https://coding.net/u/dovahkiin/p/tempData/git/raw/master/allmp3/Troll%20Warlord/Troll_death_09.mp3"
    ],
    "mp3Text": "A nasty bit of work."
  },
  {
    "type": "voice",
    "mp3Url": [
      "https://coding.net/u/dovahkiin/p/tempData/git/raw/master/allmp3/Troll%20Warlord/Troll_death_10.mp3"
    ],
    "mp3Text": "My bad."
  },
  {
    "type": "voice",
    "mp3Url": [
      "https://coding.net/u/dovahkiin/p/tempData/git/raw/master/allmp3/Troll%20Warlord/Troll_death_11.mp3"
    ],
    "mp3Text": "The last bell tolls."
  },
  {
    "type": "voice",
    "mp3Url": [
      "https://coding.net/u/dovahkiin/p/tempData/git/raw/master/allmp3/Troll%20Warlord/Troll_death_12.mp3"
    ],
    "mp3Text": "I ain't going nowhere."
  },
  {
    "type": "voice",
    "mp3Url": [
      "https://coding.net/u/dovahkiin/p/tempData/git/raw/master/allmp3/Troll%20Warlord/Troll_death_13.mp3"
    ],
    "mp3Text": "The last bell trolls."
  },
  {
    "type": "voice",
    "mp3Url": [
      "https://coding.net/u/dovahkiin/p/tempData/git/raw/master/allmp3/Troll%20Warlord/Troll_death_14.mp3"
    ],
    "mp3Text": "This is all their fault."
  },
  {
    "type": "voice",
    "mp3Url": [
      "https://coding.net/u/dovahkiin/p/tempData/git/raw/master/allmp3/Troll%20Warlord/Troll_death_15.mp3"
    ],
    "mp3Text": "Fahhhh…."
  },
  {
    "type": "voice",
    "mp3Url": [
      "https://coding.net/u/dovahkiin/p/tempData/git/raw/master/allmp3/Troll%20Warlord/Troll_death_17.mp3"
    ],
    "mp3Text": "But a troll cannot die…"
  },
  {
    "type": "voice",
    "mp3Url": [
      "https://coding.net/u/dovahkiin/p/tempData/git/raw/master/allmp3/Troll%20Warlord/Troll_unknown_01.mp3"
    ],
    "mp3Text": "Oh, come on!"
  },
  {
    "type": "voice",
    "mp3Url": [
      "https://coding.net/u/dovahkiin/p/tempData/git/raw/master/allmp3/Troll%20Warlord/Troll_unknown_02.mp3"
    ],
    "mp3Text": "Ah, come on."
  },
  {
    "type": "voice",
    "mp3Url": [
      "https://coding.net/u/dovahkiin/p/tempData/git/raw/master/allmp3/Troll%20Warlord/Troll_lose_03.mp3"
    ],
    "mp3Text": "It was everyone else's fault."
  },
  {
    "type": "voice",
    "mp3Url": [
      "https://coding.net/u/dovahkiin/p/tempData/git/raw/master/allmp3/Troll%20Warlord/Troll_lose_05.mp3"
    ],
    "mp3Text": "With this team, I didn't have a chance!"
  },
  {
    "headTitle": "Respawning",
    "type": "title"
  },
  {
    "type": "voice",
    "mp3Url": [
      "https://coding.net/u/dovahkiin/p/tempData/git/raw/master/allmp3/Troll%20Warlord/Troll_respawn_01.mp3"
    ],
    "mp3Text": "No more playing nice, just in case you thought I was."
  },
  {
    "type": "voice",
    "mp3Url": [
      "https://coding.net/u/dovahkiin/p/tempData/git/raw/master/allmp3/Troll%20Warlord/Troll_respawn_02.mp3"
    ],
    "mp3Text": "I knew I'd be back."
  },
  {
    "type": "voice",
    "mp3Url": [
      "https://coding.net/u/dovahkiin/p/tempData/git/raw/master/allmp3/Troll%20Warlord/Troll_respawn_03.mp3"
    ],
    "mp3Text": "You can't have a war without a warlord!"
  },
  {
    "type": "voice",
    "mp3Url": [
      "https://coding.net/u/dovahkiin/p/tempData/git/raw/master/allmp3/Troll%20Warlord/Troll_respawn_04.mp3"
    ],
    "mp3Text": "The past is death, the present is death, the future, yeah, more death!"
  },
  {
    "type": "voice",
    "mp3Url": [
      "https://coding.net/u/dovahkiin/p/tempData/git/raw/master/allmp3/Troll%20Warlord/Troll_respawn_05.mp3"
    ],
    "mp3Text": "Fighting a troll only makes him grow stronger."
  },
  {
    "type": "voice",
    "mp3Url": [
      "https://coding.net/u/dovahkiin/p/tempData/git/raw/master/allmp3/Troll%20Warlord/Troll_respawn_06.mp3"
    ],
    "mp3Text": "No more mister nice guy, and believe me, that's what I was."
  },
  {
    "type": "voice",
    "mp3Url": [
      "https://coding.net/u/dovahkiin/p/tempData/git/raw/master/allmp3/Troll%20Warlord/Troll_respawn_07.mp3"
    ],
    "mp3Text": "This war will end when everybody's dead."
  },
  {
    "type": "voice",
    "mp3Url": [
      "https://coding.net/u/dovahkiin/p/tempData/git/raw/master/allmp3/Troll%20Warlord/Troll_respawn_08.mp3"
    ],
    "mp3Text": "The warlord returns."
  },
  {
    "type": "voice",
    "mp3Url": [
      "https://coding.net/u/dovahkiin/p/tempData/git/raw/master/allmp3/Troll%20Warlord/Troll_respawn_09.mp3"
    ],
    "mp3Text": "I live to fight."
  },
  {
    "type": "voice",
    "mp3Url": [
      "https://coding.net/u/dovahkiin/p/tempData/git/raw/master/allmp3/Troll%20Warlord/Troll_respawn_10.mp3"
    ],
    "mp3Text": "Being dead only makes me angrier."
  },
  {
    "text": "Reincarnating",
    "type": "subTitle"
  },
  {
    "type": "voice",
    "mp3Url": [
      "https://coding.net/u/dovahkiin/p/tempData/git/raw/master/allmp3/Troll%20Warlord/Troll_fastres_01.mp3"
    ],
    "mp3Text": "Trolls always get the last word."
  },
  {
    "headTitle": "Bottling Runes",
    "type": "title"
  },
  {
    "type": "voice",
    "mp3Url": [
      "https://coding.net/u/dovahkiin/p/tempData/git/raw/master/allmp3/Troll%20Warlord/Troll_bottle_01.mp3"
    ],
    "mp3Text": "Bottled. Like my hate."
  },
  {
    "type": "voice",
    "mp3Url": [
      "https://coding.net/u/dovahkiin/p/tempData/git/raw/master/allmp3/Troll%20Warlord/Troll_bottle_02.mp3"
    ],
    "mp3Text": "I like to bottle it up until it explodes."
  },
  {
    "type": "voice",
    "mp3Url": [
      "https://coding.net/u/dovahkiin/p/tempData/git/raw/master/allmp3/Troll%20Warlord/Troll_bottle_03.mp3"
    ],
    "mp3Text": "Saved for later, to serve it up cold."
  },
  {
    "headTitle": "Activating runes",
    "type": "title"
  },
  {
    "imgUrl": "http://dota.cn-sh2.ufileos.com/16px-Arcane_Rune_minimap_icon.png",
    "skillName": "Arcane Rune",
    "type": "rune"
  },
  {
    "type": "voice",
    "mp3Url": [
      "https://coding.net/u/dovahkiin/p/tempData/git/raw/master/allmp3/Troll%20Warlord/Troll_laugh_03.mp3"
    ],
    "mp3Text": "He heh hah heh heheheh."
  },
  {
    "imgUrl": "http://dota.cn-sh2.ufileos.com/16px-Bounty_Rune_minimap_icon.png",
    "skillName": "Bounty Rune",
    "type": "rune"
  },
  {
    "type": "voice",
    "mp3Url": [
      "https://coding.net/u/dovahkiin/p/tempData/git/raw/master/allmp3/Troll%20Warlord/Troll_lasthit_01.mp3"
    ],
    "mp3Text": "Gold for my armor."
  },
  {
    "imgUrl": "http://dota.cn-sh2.ufileos.com/16px-Double_Damage_Rune_minimap_icon.png",
    "skillName": "Double Damage Rune",
    "type": "rune"
  },
  {
    "type": "voice",
    "mp3Url": [
      "https://coding.net/u/dovahkiin/p/tempData/git/raw/master/allmp3/Troll%20Warlord/Troll_doubdam_01.mp3"
    ],
    "mp3Text": "Double damage."
  },
  {
    "type": "voice",
    "mp3Url": [
      "https://coding.net/u/dovahkiin/p/tempData/git/raw/master/allmp3/Troll%20Warlord/Troll_doubdam_02.mp3"
    ],
    "mp3Text": "The crackle rune."
  },
  {
    "imgUrl": "http://dota.cn-sh2.ufileos.com/16px-Haste_Rune_minimap_icon.png",
    "skillName": "Haste Rune",
    "type": "rune"
  },
  {
    "type": "voice",
    "mp3Url": [
      "https://coding.net/u/dovahkiin/p/tempData/git/raw/master/allmp3/Troll%20Warlord/Troll_haste_01.mp3"
    ],
    "mp3Text": "Haste."
  },
  {
    "type": "voice",
    "mp3Url": [
      "https://coding.net/u/dovahkiin/p/tempData/git/raw/master/allmp3/Troll%20Warlord/Troll_haste_02.mp3"
    ],
    "mp3Text": "Ah, the red rune runs."
  },
  {
    "imgUrl": "http://dota.cn-sh2.ufileos.com/16px-Illusion_Rune_minimap_icon.png",
    "skillName": "Illusion Rune",
    "type": "rune"
  },
  {
    "type": "voice",
    "mp3Url": [
      "https://coding.net/u/dovahkiin/p/tempData/git/raw/master/allmp3/Troll%20Warlord/Troll_illus_01.mp3"
    ],
    "mp3Text": "Illusion."
  },
  {
    "type": "voice",
    "mp3Url": [
      "https://coding.net/u/dovahkiin/p/tempData/git/raw/master/allmp3/Troll%20Warlord/Troll_illus_02.mp3"
    ],
    "mp3Text": "More of me to hate."
  },
  {
    "imgUrl": "http://dota.cn-sh2.ufileos.com/16px-Invisibility_Rune_minimap_icon.png",
    "skillName": "Invisibility Rune",
    "type": "rune"
  },
  {
    "type": "voice",
    "mp3Url": [
      "https://coding.net/u/dovahkiin/p/tempData/git/raw/master/allmp3/Troll%20Warlord/Troll_invis_01.mp3"
    ],
    "mp3Text": "Invisibility."
  },
  {
    "type": "voice",
    "mp3Url": [
      "https://coding.net/u/dovahkiin/p/tempData/git/raw/master/allmp3/Troll%20Warlord/Troll_invis_03.mp3"
    ],
    "mp3Text": "Sweet anonymity."
  },
  {
    "type": "voice",
    "mp3Url": [
      "https://coding.net/u/dovahkiin/p/tempData/git/raw/master/allmp3/Troll%20Warlord/Troll_invis_02.mp3"
    ],
    "mp3Text": "Anonymity, the friend to every troll."
  },
  {
    "imgUrl": "http://dota.cn-sh2.ufileos.com/16px-Regeneration_Rune_minimap_icon.png",
    "skillName": "Regeneration Rune",
    "type": "rune"
  },
  {
    "type": "voice",
    "mp3Url": [
      "https://coding.net/u/dovahkiin/p/tempData/git/raw/master/allmp3/Troll%20Warlord/Troll_regen_01.mp3"
    ],
    "mp3Text": "Regeneration!"
  },
  {
    "type": "voice",
    "mp3Url": [
      "https://coding.net/u/dovahkiin/p/tempData/git/raw/master/allmp3/Troll%20Warlord/Troll_regen_02.mp3"
    ],
    "mp3Text": "Green like my envy."
  },
  {
    "headTitle": "Ability on cooldown",
    "type": "title"
  },
  {
    "voices": []
  },
  {
    "text": "First attempt within 10 seconds",
    "type": "small"
  },
  {
    "type": "voice",
    "mp3Url": [
      "https://coding.net/u/dovahkiin/p/tempData/git/raw/master/allmp3/Troll%20Warlord/Troll_notyet_02.mp3"
    ],
    "mp3Text": "Not yet."
  },
  {
    "type": "voice",
    "mp3Url": [
      "https://coding.net/u/dovahkiin/p/tempData/git/raw/master/allmp3/Troll%20Warlord/Troll_notyet_09.mp3"
    ],
    "mp3Text": "I'm not ready."
  },
  {
    "type": "voice",
    "mp3Url": [
      "https://coding.net/u/dovahkiin/p/tempData/git/raw/master/allmp3/Troll%20Warlord/Troll_notyet_13.mp3"
    ],
    "mp3Text": "It's not time yet."
  },
  {
    "text": "Second attempt within 10 seconds",
    "type": "small"
  },
  {
    "type": "voice",
    "mp3Url": [
      "https://coding.net/u/dovahkiin/p/tempData/git/raw/master/allmp3/Troll%20Warlord/Troll_notyet_03.mp3"
    ],
    "mp3Text": "Not yet."
  },
  {
    "type": "voice",
    "mp3Url": [
      "https://coding.net/u/dovahkiin/p/tempData/git/raw/master/allmp3/Troll%20Warlord/Troll_notyet_10.mp3"
    ],
    "mp3Text": "I'm not ready."
  },
  {
    "type": "voice",
    "mp3Url": [
      "https://coding.net/u/dovahkiin/p/tempData/git/raw/master/allmp3/Troll%20Warlord/Troll_notyet_14.mp3"
    ],
    "mp3Text": "It's not time yet."
  },
  {
    "text": "Third and more attempts within 10 seconds",
    "type": "small"
  },
  {
    "type": "voice",
    "mp3Url": [
      "https://coding.net/u/dovahkiin/p/tempData/git/raw/master/allmp3/Troll%20Warlord/Troll_notyet_04.mp3"
    ],
    "mp3Text": "I will kill you."
  },
  {
    "type": "voice",
    "mp3Url": [
      "https://coding.net/u/dovahkiin/p/tempData/git/raw/master/allmp3/Troll%20Warlord/Troll_notyet_11.mp3"
    ],
    "mp3Text": "Now I'm ready, to stab you."
  },
  {
    "type": "voice",
    "mp3Url": [
      "https://coding.net/u/dovahkiin/p/tempData/git/raw/master/allmp3/Troll%20Warlord/Troll_notyet_15.mp3"
    ],
    "mp3Text": "It is time to gut you."
  },
  {
    "headTitle": "Not enough mana",
    "type": "title"
  },
  {
    "voices": []
  },
  {
    "text": "First attempt within 10 seconds",
    "type": "small"
  },
  {
    "type": "voice",
    "mp3Url": [
      "https://coding.net/u/dovahkiin/p/tempData/git/raw/master/allmp3/Troll%20Warlord/Troll_nomana_02.mp3"
    ],
    "mp3Text": "Out of mana."
  },
  {
    "type": "voice",
    "mp3Url": [
      "https://coding.net/u/dovahkiin/p/tempData/git/raw/master/allmp3/Troll%20Warlord/Troll_nomana_04.mp3"
    ],
    "mp3Text": "No mana."
  },
  {
    "type": "voice",
    "mp3Url": [
      "https://coding.net/u/dovahkiin/p/tempData/git/raw/master/allmp3/Troll%20Warlord/Troll_nomana_07.mp3"
    ],
    "mp3Text": "Not enough mana."
  },
  {
    "text": "Second attempt within 10 seconds",
    "type": "small"
  },
  {
    "type": "voice",
    "mp3Url": [
      "https://coding.net/u/dovahkiin/p/tempData/git/raw/master/allmp3/Troll%20Warlord/Troll_nomana_03.mp3"
    ],
    "mp3Text": "Out of mana."
  },
  {
    "type": "voice",
    "mp3Url": [
      "https://coding.net/u/dovahkiin/p/tempData/git/raw/master/allmp3/Troll%20Warlord/Troll_nomana_05.mp3"
    ],
    "mp3Text": "No mana."
  },
  {
    "type": "voice",
    "mp3Url": [
      "https://coding.net/u/dovahkiin/p/tempData/git/raw/master/allmp3/Troll%20Warlord/Troll_nomana_08.mp3"
    ],
    "mp3Text": "Not enough mana."
  },
  {
    "text": "Third and more attempts within 10 seconds",
    "type": "small"
  },
  {
    "type": "voice",
    "mp3Url": [
      "https://coding.net/u/dovahkiin/p/tempData/git/raw/master/allmp3/Troll%20Warlord/Troll_notyet_05.mp3"
    ],
    "mp3Text": "Do that again, and I will kill you."
  },
  {
    "type": "voice",
    "mp3Url": [
      "https://coding.net/u/dovahkiin/p/tempData/git/raw/master/allmp3/Troll%20Warlord/Troll_nomana_06.mp3"
    ],
    "mp3Text": "No mana."
  },
  {
    "type": "voice",
    "mp3Url": [
      "https://coding.net/u/dovahkiin/p/tempData/git/raw/master/allmp3/Troll%20Warlord/Troll_nomana_09.mp3"
    ],
    "mp3Text": "Not enough mana."
  },
  {
    "headTitle": "Taking damage",
    "type": "title"
  },
  {
    "type": "voice",
    "mp3Url": [
      "https://coding.net/u/dovahkiin/p/tempData/git/raw/master/allmp3/Troll%20Warlord/Troll_pain_01.mp3"
    ],
    "mp3Text": "Deh!"
  },
  {
    "type": "voice",
    "mp3Url": [
      "https://coding.net/u/dovahkiin/p/tempData/git/raw/master/allmp3/Troll%20Warlord/Troll_pain_02.mp3"
    ],
    "mp3Text": "Dueh."
  },
  {
    "type": "voice",
    "mp3Url": [
      "https://coding.net/u/dovahkiin/p/tempData/git/raw/master/allmp3/Troll%20Warlord/Troll_pain_03.mp3"
    ],
    "mp3Text": "Gnaae."
  },
  {
    "type": "voice",
    "mp3Url": [
      "https://coding.net/u/dovahkiin/p/tempData/git/raw/master/allmp3/Troll%20Warlord/Troll_pain_04.mp3"
    ],
    "mp3Text": "Gnarg."
  },
  {
    "type": "voice",
    "mp3Url": [
      "https://coding.net/u/dovahkiin/p/tempData/git/raw/master/allmp3/Troll%20Warlord/Troll_pain_05.mp3"
    ],
    "mp3Text": "Agh."
  },
  {
    "type": "voice",
    "mp3Url": [
      "https://coding.net/u/dovahkiin/p/tempData/git/raw/master/allmp3/Troll%20Warlord/Troll_pain_07.mp3"
    ],
    "mp3Text": "Blegh."
  },
  {
    "type": "voice",
    "mp3Url": [
      "https://coding.net/u/dovahkiin/p/tempData/git/raw/master/allmp3/Troll%20Warlord/Troll_pain_08.mp3"
    ],
    "mp3Text": "Blegh."
  },
  {
    "type": "voice",
    "mp3Url": [
      "https://coding.net/u/dovahkiin/p/tempData/git/raw/master/allmp3/Troll%20Warlord/Troll_pain_09.mp3"
    ],
    "mp3Text": "Heghl."
  },
  {
    "type": "voice",
    "mp3Url": [
      "https://coding.net/u/dovahkiin/p/tempData/git/raw/master/allmp3/Troll%20Warlord/Troll_underattack_01.mp3"
    ],
    "mp3Text": "Nah, I'm under attack!"
  },
  {
    "type": "voice",
    "mp3Url": [
      "https://coding.net/u/dovahkiin/p/tempData/git/raw/master/allmp3/Troll%20Warlord/Troll_underattack_03.mp3"
    ],
    "mp3Text": "Get off your ass and help me!"
  },
  {
    "headTitle": "Selecting",
    "type": "title"
  },
  {
    "text": "5 consecutive clicks on the hero",
    "type": "small"
  },
  {
    "type": "voice",
    "mp3Url": [
      "https://coding.net/u/dovahkiin/p/tempData/git/raw/master/allmp3/Troll%20Warlord/Troll_rare_01.mp3"
    ],
    "mp3Text": "I suffer the innocents and guilty alike. There are no innocents."
  },
  {
    "type": "voice",
    "mp3Url": [
      "https://coding.net/u/dovahkiin/p/tempData/git/raw/master/allmp3/Troll%20Warlord/Troll_rare_02.mp3"
    ],
    "mp3Text": "The strong eat the weak, and I eat the strong."
  },
  {
    "type": "voice",
    "mp3Url": [
      "https://coding.net/u/dovahkiin/p/tempData/git/raw/master/allmp3/Troll%20Warlord/Troll_rare_03.mp3"
    ],
    "mp3Text": "And they said I'd never survive outside my mother's den."
  },
  {
    "type": "voice",
    "mp3Url": [
      "https://coding.net/u/dovahkiin/p/tempData/git/raw/master/allmp3/Troll%20Warlord/Troll_unknown_03.mp3"
    ],
    "mp3Text": "I'm not even sure why I'm so mad."
  },
  {
    "type": "voice",
    "mp3Url": [
      "https://coding.net/u/dovahkiin/p/tempData/git/raw/master/allmp3/Troll%20Warlord/Troll_unknown_06.mp3"
    ],
    "mp3Text": "Why am I angry for no reason?"
  },
  {
    "type": "voice",
    "mp3Url": [
      "https://coding.net/u/dovahkiin/p/tempData/git/raw/master/allmp3/Troll%20Warlord/Troll_unknown_08.mp3"
    ],
    "mp3Text": "Sometimes you just wake up on the wrong side of the bed."
  },
  {
    "type": "voice",
    "mp3Url": [
      "https://coding.net/u/dovahkiin/p/tempData/git/raw/master/allmp3/Troll%20Warlord/Troll_unknown_09.mp3"
    ],
    "mp3Text": "Why doesn't anybody like me?"
  },
  {
    "headTitle": "Chat responses",
    "type": "title"
  },
  {
    "text": "Lane missing",
    "type": "subTitle"
  },
  {
    "type": "voice",
    "mp3Url": [
      "https://coding.net/u/dovahkiin/p/tempData/git/raw/master/allmp3/Troll%20Warlord/Troll_lanemissing_01.mp3"
    ],
    "mp3Text": "Missing top."
  },
  {
    "type": "voice",
    "mp3Url": [
      "https://coding.net/u/dovahkiin/p/tempData/git/raw/master/allmp3/Troll%20Warlord/Troll_lanemissing_02.mp3"
    ],
    "mp3Text": "Missing middle."
  },
  {
    "type": "voice",
    "mp3Url": [
      "https://coding.net/u/dovahkiin/p/tempData/git/raw/master/allmp3/Troll%20Warlord/Troll_lanemissing_03.mp3"
    ],
    "mp3Text": "Missing bottom."
  },
  {
    "text": "Thanking",
    "type": "subTitle"
  },
  {
    "type": "voice",
    "mp3Url": [
      "https://coding.net/u/dovahkiin/p/tempData/git/raw/master/allmp3/Troll%20Warlord/Troll_thanks_01.mp3"
    ],
    "mp3Text": "It's about time."
  },
  {
    "type": "voice",
    "mp3Url": [
      "https://coding.net/u/dovahkiin/p/tempData/git/raw/master/allmp3/Troll%20Warlord/Troll_thanks_02.mp3"
    ],
    "mp3Text": "Took you long enough."
  },
  {
    "type": "voice",
    "mp3Url": [
      "https://coding.net/u/dovahkiin/p/tempData/git/raw/master/allmp3/Troll%20Warlord/Troll_thanks_03.mp3"
    ],
    "mp3Text": "I'm still going to kill you later."
  },
  {
    "type": "voice",
    "mp3Url": [
      "https://coding.net/u/dovahkiin/p/tempData/git/raw/master/allmp3/Troll%20Warlord/Troll_thanks_04.mp3"
    ],
    "mp3Text": "Next time, be quicker about it."
  },
  {
    "type": "voice",
    "mp3Url": [
      "https://coding.net/u/dovahkiin/p/tempData/git/raw/master/allmp3/Troll%20Warlord/Troll_thanks_05.mp3"
    ],
    "mp3Text": "No, I do not do a high five."
  },
  {
    "text": "Laughing",
    "type": "subTitle"
  },
  {
    "type": "voice",
    "mp3Url": [
      "https://coding.net/u/dovahkiin/p/tempData/git/raw/master/allmp3/Troll%20Warlord/Troll_laugh_02.mp3"
    ],
    "mp3Text": "Yeheheheheh."
  },
  {
    "type": "voice",
    "mp3Url": [
      "https://coding.net/u/dovahkiin/p/tempData/git/raw/master/allmp3/Troll%20Warlord/Troll_laugh_03.mp3"
    ],
    "mp3Text": "He heh hah heh heheheh."
  },
  {
    "type": "voice",
    "mp3Url": [
      "https://coding.net/u/dovahkiin/p/tempData/git/raw/master/allmp3/Troll%20Warlord/Troll_laugh_04.mp3"
    ],
    "mp3Text": "Hahahahahah."
  },
  {
    "type": "voice",
    "mp3Url": [
      "https://coding.net/u/dovahkiin/p/tempData/git/raw/master/allmp3/Troll%20Warlord/Troll_laugh_05.mp3"
    ],
    "mp3Text": "Yaaahahahaahhah."
  },
  {
    "type": "voice",
    "mp3Url": [
      "https://coding.net/u/dovahkiin/p/tempData/git/raw/master/allmp3/Troll%20Warlord/Troll_laugh_07.mp3"
    ],
    "mp3Text": "Heheheh."
  },
  {
    "type": "voice",
    "mp3Url": [
      "https://coding.net/u/dovahkiin/p/tempData/git/raw/master/allmp3/Troll%20Warlord/Troll_unknown_04.mp3"
    ],
    "mp3Text": "I'm not even sure why I'm so mad."
  },
  {
    "headTitle": "Match end",
    "type": "title"
  },
  {
    "text": "Won",
    "type": "middle"
  },
  {
    "type": "voice",
    "mp3Url": [
      "https://coding.net/u/dovahkiin/p/tempData/git/raw/master/allmp3/Troll%20Warlord/Troll_lose_07.mp3"
    ],
    "mp3Text": "Yes!"
  },
  {
    "type": "voice",
    "mp3Url": [
      "https://coding.net/u/dovahkiin/p/tempData/git/raw/master/allmp3/Troll%20Warlord/Troll_win_01.mp3"
    ],
    "mp3Text": "Victory!"
  },
  {
    "type": "voice",
    "mp3Url": [
      "https://coding.net/u/dovahkiin/p/tempData/git/raw/master/allmp3/Troll%20Warlord/Troll_win_02.mp3"
    ],
    "mp3Text": "I carried us to victory!"
  },
  {
    "type": "voice",
    "mp3Url": [
      "https://coding.net/u/dovahkiin/p/tempData/git/raw/master/allmp3/Troll%20Warlord/Troll_win_03.mp3"
    ],
    "mp3Text": "Even with this team, I managed to win."
  },
  {
    "text": "Lost",
    "type": "middle"
  },
  {
    "type": "voice",
    "mp3Url": [
      "https://coding.net/u/dovahkiin/p/tempData/git/raw/master/allmp3/Troll%20Warlord/Troll_lose_01.mp3"
    ],
    "mp3Text": "No."
  },
  {
    "type": "voice",
    "mp3Url": [
      "https://coding.net/u/dovahkiin/p/tempData/git/raw/master/allmp3/Troll%20Warlord/Troll_lose_02.mp3"
    ],
    "mp3Text": "Defeated."
  },
  {
    "type": "voice",
    "mp3Url": [
      "https://coding.net/u/dovahkiin/p/tempData/git/raw/master/allmp3/Troll%20Warlord/Troll_lose_10.mp3"
    ],
    "mp3Text": "Don't look at me. I did everything right."
  },
  {
    "type": "voice",
    "mp3Url": [
      "https://coding.net/u/dovahkiin/p/tempData/git/raw/master/allmp3/Troll%20Warlord/Troll_failure_04.mp3"
    ],
    "mp3Text": "I'm going home."
  },
  {
    "type": "voice",
    "mp3Url": [
      "https://coding.net/u/dovahkiin/p/tempData/git/raw/master/allmp3/Troll%20Warlord/Troll_lose_04.mp3"
    ],
    "mp3Text": "If I had a decent team, this never would have happened."
  },
  {
    "type": "voice",
    "mp3Url": [
      "https://coding.net/u/dovahkiin/p/tempData/git/raw/master/allmp3/Troll%20Warlord/Troll_lose_06.mp3"
    ],
    "mp3Text": "Why do I always get the worst teams?"
  },
  {
    "type": "voice",
    "mp3Url": [
      "https://coding.net/u/dovahkiin/p/tempData/git/raw/master/allmp3/Troll%20Warlord/Troll_lose_08.mp3"
    ],
    "mp3Text": "I knew I should have gone to bed instead."
  },
  {
    "headTitle": "Cosmetic item drop",
    "type": "title"
  },
  {
    "text": "Common",
    "type": "middle"
  },
  {
    "type": "voice",
    "mp3Url": [
      "https://coding.net/u/dovahkiin/p/tempData/git/raw/master/allmp3/Troll%20Warlord/Troll_drop_common_01.mp3"
    ],
    "mp3Text": "What the hell is this?"
  },
  {
    "text": "Uncommon",
    "type": "middle"
  },
  {
    "type": "voice",
    "mp3Url": [
      "https://coding.net/u/dovahkiin/p/tempData/git/raw/master/allmp3/Troll%20Warlord/Troll_drop_med_01.mp3"
    ],
    "mp3Text": "Wait, who's giving me presents?"
  },
  {
    "text": "Rare and higher",
    "type": "middle"
  },
  {
    "type": "voice",
    "mp3Url": [
      "https://coding.net/u/dovahkiin/p/tempData/git/raw/master/allmp3/Troll%20Warlord/Troll_drop_rare_01.mp3"
    ],
    "mp3Text": "Oh, I deserve this for being so nice."
  }
]